[{"id":"bitcoin","symbol":"btc","name":"Bitcoin","image":"https://coin-images.coingecko.com/coins/images/1/large/bitcoin.png?1696501400","current_price":57850,"market_cap":1143953959926,"market_cap_rank":1,"fully_diluted_valuation":1218231074858,"total_volume":20473289600,"high_24h":58430,"low_24h":56089,"price_change_24h":1392.03,"price_change_percentage_24h":2.4656,"market_cap_change_24h":31413976715,"market_cap_change_percentage_24h":2.82363,"circulating_supply":19719603.0,"total_supply":21000000.0,"max_supply":21000000.0,"ath":73738,"ath_change_percentage":-21.31401,"ath_date":"2024-03-14T07:10:36.635Z","atl":67.81,"atl_change_percentage":85465.96912,"atl_date":"2013-07-06T00:00:00.000Z","roi":null,"last_updated":"2024-07-07T01:27:34.852Z"},{"id":"ethereum","symbol":"eth","name":"Ethereum","image":"https://coin-images.coingecko.com/coins/images/279/large/ethereum.png?1696501628","current_price":3041.07,"market_cap":366852543614,"market_cap_rank":2,"fully_diluted_valuation":366853234306,"total_volume":10413147376,"high_24h":3076.26,"low_24h":2959.25,"price_change_24h":66.67,"price_change_percentage_24h":2.24137,"market_cap_change_24h":9299739458,"market_cap_change_percentage_24h":2.60094,"circulating_supply":120198146.00913,"total_supply":120198372.312523,"max_supply":null,"ath":4878.26,"ath_change_percentage":-37.43174,"ath_date":"2021-11-10T14:24:19.604Z","atl":0.432979,"atl_change_percentage":704840.38253,"atl_date":"2015-10-20T00:00:00.000Z","roi":{"times":69.25542409123011,"currency":"btc","percentage":6925.542409123012},"last_updated":"2024-07-07T01:27:45.126Z"},{"id":"tether","symbol":"usdt","name":"Tether","image":"https://coin-images.coingecko.com/coins/images/325/large/Tether.png?1696501661","current_price":0.999893,"market_cap":112301406899,"market_cap_rank":3,"fully_diluted_valuation":112301406899,"total_volume":31155701901,"high_24h":1.003,"low_24h":0.99781,"price_change_24h":-0.000363865732973756,"price_change_percentage_24h":-0.03638,"market_cap_change_24h":48747283,"market_cap_change_percentage_24h":0.04343,"circulating_supply":112223789756.28,"total_supply":112223789756.28,"max_supply":null,"ath":1.32,"ath_change_percentage":-24.40982,"ath_date":"2018-07-24T00:00:00.000Z","atl":0.572521,"atl_change_percentage":74.68882,"atl_date":"2015-03-02T00:00:00.000Z","roi":null,"last_updated":"2024-07-07T01:25:43.613Z"},{"id":"binancecoin","symbol":"bnb","name":"BNB","image":"https://coin-images.coingecko.com/coins/images/825/large/bnb-icon2_2x.png?1696501970","current_price":517.79,"market_cap":79952891028,"market_cap_rank":4,"fully_diluted_valuation":79952891028,"total_volume":773863105,"high_24h":530.91,"low_24h":497.09,"price_change_24h":16.87,"price_change_percentage_24h":3.36838,"market_cap_change_24h":3014916784,"market_cap_change_percentage_24h":3.91863,"circulating_supply":153856150.0,"total_supply":153856150.0,"max_supply":200000000.0,"ath":717.48,"ath_change_percentage":-27.57103,"ath_date":"2024-06-06T14:10:59.816Z","atl":0.0398177,"atl_change_percentage":1304998.14346,"atl_date":"2017-10-19T00:00:00.000Z","roi":null,"last_updated":"2024-07-07T01:27:28.294Z"},{"id":"solana","symbol":"sol","name":"Solana","image":"https://coin-images.coingecko.com/coins/images/4128/large/solana.png?1718769756","current_price":140.54,"market_cap":65353584518,"market_cap_rank":5,"fully_diluted_valuation":81727142959,"total_volume":2397805235,"high_24h":143.97,"low_24h":132.66,"price_change_24h":5.85,"price_change_percentage_24h":4.34627,"market_cap_change_24h":3137380952,"market_cap_change_percentage_24h":5.04271,"circulating_supply":463551528.648016,"total_supply":579688816.304306,"max_supply":null,"ath":259.96,"ath_change_percentage":-45.6812,"ath_date":"2021-11-06T21:54:35.825Z","atl":0.500801,"atl_change_percentage":28096.16848,"atl_date":"2020-05-11T19:35:23.449Z","roi":null,"last_updated":"2024-07-07T01:27:25.372Z"},{"id":"usd-coin","symbol":"usdc","name":"USDC","image":"https://coin-images.coingecko.com/coins/images/6319/large/usdc.png?1696506694","current_price":0.999096,"market_cap":33704703288,"market_cap_rank":6,"fully_diluted_valuation":33704738556,"total_volume":3725311771,"high_24h":1.003,"low_24h":0.997896,"price_change_24h":-0.00099206479741587,"price_change_percentage_24h":-0.0992,"market_cap_change_24h":107602173,"market_cap_change_percentage_24h":0.32027,"circulating_supply":33721429568.6196,"total_supply":33721464854.3821,"max_supply":null,"ath":1.17,"ath_change_percentage":-14.70294,"ath_date":"2019-05-08T00:40:28.300Z","atl":0.877647,"atl_change_percentage":13.97342,"atl_date":"2023-03-11T08:02:13.981Z","roi":null,"last_updated":"2024-07-07T01:27:52.385Z"},{"id":"staked-ether","symbol":"steth","name":"Lido Staked Ether","image":"https://coin-images.coingecko.com/coins/images/13442/large/steth_logo.png?1696513206","current_price":3040.22,"market_cap":29659892889,"market_cap_rank":7,"fully_diluted_valuation":29659892889,"total_volume":64345697,"high_24h":3074.45,"low_24h":2954.82,"price_change_24h":67.17,"price_change_percentage_24h":2.25938,"market_cap_change_24h":684295018,"market_cap_change_percentage_24h":2.36163,"circulating_supply":9741785.99824169,"total_supply":9741785.99824169,"max_supply":null,"ath":4829.57,"ath_change_percentage":-36.92028,"ath_date":"2021-11-10T14:40:47.256Z","atl":482.9,"atl_change_percentage":530.87669,"atl_date":"2020-12-22T04:08:21.854Z","roi":null,"last_updated":"2024-07-07T01:27:44.038Z"},{"id":"ripple","symbol":"xrp","name":"XRP","image":"https://coin-images.coingecko.com/coins/images/44/large/xrp-symbol-white-128.png?1696501442","current_price":0.443958,"market_cap":24800538625,"market_cap_rank":8,"fully_diluted_valuation":44501199051,"total_volume":690409999,"high_24h":0.449565,"low_24h":0.424442,"price_change_24h":0.01655701,"price_change_percentage_24h":3.87388,"market_cap_change_24h":1023853655,"market_cap_change_percentage_24h":4.30612,"circulating_supply":55723063839.0,"total_supply":99987471767.0,"max_supply":100000000000.0,"ath":3.4,"ath_change_percentage":-86.87801,"ath_date":"2018-01-07T00:00:00.000Z","atl":0.00268621,"atl_change_percentage":16501.26486,"atl_date":"2014-05-22T00:00:00.000Z","roi":null,"last_updated":"2024-07-07T01:27:45.969Z"},{"id":"the-open-network","symbol":"ton","name":"Toncoin","image":"https://coin-images.coingecko.com/coins/images/17980/large/ton_symbol.png?1696517498","current_price":7.46,"market_cap":18719040453,"market_cap_rank":9,"fully_diluted_valuation":38159133402,"total_volume":418800626,"high_24h":7.71,"low_24h":7.23,"price_change_24h":0.193159,"price_change_percentage_24h":2.65933,"market_cap_change_24h":572125224,"market_cap_change_percentage_24h":3.15274,"circulating_supply":2506049374.24442,"total_supply":5108631108.6567,"max_supply":null,"ath":8.25,"ath_change_percentage":-9.48499,"ath_date":"2024-06-15T00:36:51.509Z","atl":0.519364,"atl_change_percentage":1338.44317,"atl_date":"2021-09-21T00:33:11.092Z","roi":null,"last_updated":"2024-07-07T01:27:34.305Z"},{"id":"dogecoin","symbol":"doge","name":"Dogecoin","image":"https://coin-images.coingecko.com/coins/images/5/large/dogecoin.png?1696501409","current_price":0.110679,"market_cap":16116408195,"market_cap_rank":10,"fully_diluted_valuation":16123680015,"total_volume":818920100,"high_24h":0.113971,"low_24h":0.104989,"price_change_24h":0.0038024,"price_change_percentage_24h":3.55773,"market_cap_change_24h":702231559,"market_cap_change_percentage_24h":4.55575,"circulating_supply":144944876383.705,"total_supply":145010276383.705,"max_supply":null,"ath":0.731578,"ath_change_percentage":-84.79612,"ath_date":"2021-05-08T05:08:23.458Z","atl":8.69e-05,"atl_change_percentage":127890.13933,"atl_date":"2015-05-06T00:00:00.000Z","roi":null,"last_updated":"2024-07-07T01:27:48.911Z"},{"id":"cardano","symbol":"ada","name":"Cardano","image":"https://coin-images.coingecko.com/coins/images/975/large/cardano.png?1696502090","current_price":0.36697,"market_cap":13060862280,"market_cap_rank":11,"fully_diluted_valuation":16584782667,"total_volume":289300275,"high_24h":0.37294,"low_24h":0.347986,"price_change_24h":0.01577061,"price_change_percentage_24h":4.4905,"market_cap_change_24h":634961630,"market_cap_change_percentage_24h":5.10998,"circulating_supply":35438438621.2524,"total_supply":45000000000.0,"max_supply":45000000000.0,"ath":3.09,"ath_change_percentage":-88.05941,"ath_date":"2021-09-02T06:00:10.474Z","atl":0.01925275,"atl_change_percentage":1814.50837,"atl_date":"2020-03-13T02:22:55.044Z","roi":null,"last_updated":"2024-07-07T01:27:38.918Z"},{"id":"tron","symbol":"trx","name":"TRON","image":"https://coin-images.coingecko.com/coins/images/1094/large/tron-logo.png?1696502193","current_price":0.130653,"market_cap":11398784250,"market_cap_rank":12,"fully_diluted_valuation":11398799687,"total_volume":383758462,"high_24h":0.130951,"low_24h":0.126782,"price_change_24h":0.0034781,"price_change_percentage_24h":2.73489,"market_cap_change_24h":327412111,"market_cap_change_percentage_24h":2.95729,"circulating_supply":87161829710.9497,"total_supply":87161947749.3219,"max_supply":null,"ath":0.231673,"ath_change_percentage":-43.4791,"ath_date":"2018-01-05T00:00:00.000Z","atl":0.00180434,"atl_change_percentage":7157.13576,"atl_date":"2017-11-12T00:00:00.000Z","roi":{"times":67.76493126734837,"currency":"usd","percentage":6776.493126734837},"last_updated":"2024-07-07T01:27:35.986Z"},{"id":"avalanche-2","symbol":"avax","name":"Avalanche","image":"https://coin-images.coingecko.com/coins/images/12559/large/Avalanche_Circle_RedWhite_Trans.png?1696512369","current_price":26.65,"market_cap":10570424800,"market_cap_rank":13,"fully_diluted_valuation":11893370558,"total_volume":298404498,"high_24h":27.51,"low_24h":25.0,"price_change_24h":1.55,"price_change_percentage_24h":6.15401,"market_cap_change_24h":714830594,"market_cap_change_percentage_24h":7.25304,"circulating_supply":394280557.242901,"total_supply":443626898.627828,"max_supply":720000000.0,"ath":144.96,"ath_change_percentage":-81.53964,"ath_date":"2021-11-21T14:18:56.538Z","atl":2.8,"atl_change_percentage":855.36433,"atl_date":"2020-12-31T13:15:21.540Z","roi":null,"last_updated":"2024-07-07T01:27:49.842Z"},{"id":"shiba-inu","symbol":"shib","name":"Shiba Inu","image":"https://coin-images.coingecko.com/coins/images/11939/large/shiba.png?1696511800","current_price":1.686e-05,"market_cap":10011631099,"market_cap_rank":14,"fully_diluted_valuation":16989819456,"total_volume":498022643,"high_24h":1.75e-05,"low_24h":1.475e-05,"price_change_24h":1.73e-06,"price_change_percentage_24h":11.42449,"market_cap_change_24h":1112209204,"market_cap_change_percentage_24h":12.49754,"circulating_supply":589261964558851.2,"total_supply":999982349611940.0,"max_supply":null,"ath":8.616e-05,"ath_change_percentage":-80.30473,"ath_date":"2021-10-28T03:54:55.568Z","atl":5.6366e-11,"atl_change_percentage":30105084.80166,"atl_date":"2020-11-28T11:26:25.838Z","roi":null,"last_updated":"2024-07-07T01:27:55.862Z"},{"id":"wrapped-bitcoin","symbol":"wbtc","name":"Wrapped Bitcoin","image":"https://coin-images.coingecko.com/coins/images/7598/large/wrapped_bitcoin_wbtc.png?1696507857","current_price":57842,"market_cap":8860915564,"market_cap_rank":15,"fully_diluted_valuation":8860915564,"total_volume":154810121,"high_24h":58360,"low_24h":56122,"price_change_24h":1390.09,"price_change_percentage_24h":2.46244,"market_cap_change_24h":227726217,"market_cap_change_percentage_24h":2.6378,"circulating_supply":153021.34750775,"total_supply":153021.34750775,"max_supply":153021.34750775,"ath":73505,"ath_change_percentage":-21.12447,"ath_date":"2024-03-14T07:10:23.403Z","atl":3139.17,"atl_change_percentage":1746.91471,"atl_date":"2019-04-02T00:00:00.000Z","roi":null,"last_updated":"2024-07-07T01:27:32.662Z"},{"id":"polkadot","symbol":"dot","name":"Polkadot","image":"https://coin-images.coingecko.com/coins/images/12171/large/polkadot.png?1696512008","current_price":6.2,"market_cap":8615337126,"market_cap_rank":16,"fully_diluted_valuation":9118983234,"total_volume":347173856,"high_24h":6.3,"low_24h":5.64,"price_change_24h":0.542578,"price_change_percentage_24h":9.5893,"market_cap_change_24h":797886159,"market_cap_change_percentage_24h":10.20647,"circulating_supply":1384710538.60601,"total_supply":1465659671.79225,"max_supply":null,"ath":54.98,"ath_change_percentage":-88.64717,"ath_date":"2021-11-04T14:10:09.301Z","atl":2.7,"atl_change_percentage":131.39923,"atl_date":"2020-08-20T05:48:11.359Z","roi":null,"last_updated":"2024-07-07T01:27:58.837Z"},{"id":"chainlink","symbol":"link","name":"Chainlink","image":"https://coin-images.coingecko.com/coins/images/877/large/chainlink-new-logo.png?1696502009","current_price":13.03,"market_cap":7962202316,"market_cap_rank":17,"fully_diluted_valuation":13093574563,"total_volume":313169190,"high_24h":13.26,"low_24h":12.22,"price_change_24h":0.731881,"price_change_percentage_24h":5.95275,"market_cap_change_24h":497722752,"market_cap_change_percentage_24h":6.66788,"circulating_supply":608099971.3083414,"total_supply":1000000000.0,"max_supply":1000000000.0,"ath":52.7,"ath_change_percentage":-75.13239,"ath_date":"2021-05-10T00:13:57.214Z","atl":0.148183,"atl_change_percentage":8743.36636,"atl_date":"2017-11-29T00:00:00.000Z","roi":null,"last_updated":"2024-07-07T01:27:29.729Z"},{"id":"bitcoin-cash","symbol":"bch","name":"Bitcoin Cash","image":"https://coin-images.coingecko.com/coins/images/780/large/bitcoin-cash-circle.png?1696501932","current_price":336.63,"market_cap":6679492527,"market_cap_rank":18,"fully_diluted_valuation":7109698065,"total_volume":186509170,"high_24h":343.45,"low_24h":320.38,"price_change_24h":8.73,"price_change_percentage_24h":2.6622,"market_cap_change_24h":220245674,"market_cap_change_percentage_24h":3.40977,"circulating_supply":19729296.7716508,"total_supply":21000000.0,"max_supply":21000000.0,"ath":3785.82,"ath_change_percentage":-91.05723,"ath_date":"2017-12-20T00:00:00.000Z","atl":76.93,"atl_change_percentage":340.05713,"atl_date":"2018-12-16T00:00:00.000Z","roi":null,"last_updated":"2024-07-07T01:27:42.392Z"},{"id":"uniswap","symbol":"uni","name":"Uniswap","image":"https://coin-images.coingecko.com/coins/images/12504/large/uni.jpg?1696512319","current_price":8.08,"market_cap":6115800927,"market_cap_rank":19,"fully_diluted_valuation":8113652665,"total_volume":145634712,"high_24h":8.25,"low_24h":7.68,"price_change_24h":0.292816,"price_change_percentage_24h":3.76167,"market_cap_change_24h":265865556,"market_cap_change_percentage_24h":4.54476,"circulating_supply":753766667.0,"total_supply":1000000000.0,"max_supply":1000000000.0,"ath":44.92,"ath_change_percentage":-81.91575,"ath_date":"2021-05-03T05:25:04.822Z","atl":1.03,"atl_change_percentage":688.51921,"atl_date":"2020-09-17T01:20:38.214Z","roi":null,"last_updated":"2024-07-07T01:27:49.641Z"},{"id":"dai","symbol":"dai","name":"Dai","image":"https://coin-images.coingecko.com/coins/images/9956/large/Badge_Dai.png?1696509996","current_price":0.999632,"market_cap":5336671209,"market_cap_rank":20,"fully_diluted_valuation":5336671209,"total_volume":806294667,"high_24h":1.002,"low_24h":0.997473,"price_change_24h":-0.001230326060115639,"price_change_percentage_24h":-0.12293,"market_cap_change_24h":128079962,"market_cap_change_percentage_24h":2.45901,"circulating_supply":5337720787.55667,"total_supply":5337720787.55667,"max_supply":null,"ath":1.22,"ath_change_percentage":-17.977,"ath_date":"2020-03-13T03:02:50.373Z","atl":0.88196,"atl_change_percentage":13.36155,"atl_date":"2023-03-11T07:50:50.514Z","roi":null,"last_updated":"2024-07-07T01:25:40.586Z"},{"id":"leo-token","symbol":"leo","name":"LEO Token","image":"https://coin-images.coingecko.com/coins/images/8418/large/leo-token.png?1696508607","current_price":5.74,"market_cap":5319155371,"market_cap_rank":21,"fully_diluted_valuation":5659071371,"total_volume":4748468,"high_24h":5.8,"low_24h":5.66,"price_change_24h":0.04366577,"price_change_percentage_24h":0.76593,"market_cap_change_24h":24330790,"market_cap_change_percentage_24h":0.45952,"circulating_supply":926060417.9,"total_supply":985239504.0,"max_supply":null,"ath":8.14,"ath_change_percentage":-29.37046,"ath_date":"2022-02-08T17:40:10.285Z","atl":0.799859,"atl_change_percentage":618.37092,"atl_date":"2019-12-24T15:14:35.376Z","roi":null,"last_updated":"2024-07-07T01:27:35.281Z"},{"id":"near","symbol":"near","name":"NEAR Protocol","image":"https://coin-images.coingecko.com/coins/images/10365/large/near.jpg?1696510367","current_price":4.72,"market_cap":5193800114,"market_cap_rank":22,"fully_diluted_valuation":5615943633,"total_volume":215247106,"high_24h":4.85,"low_24h":4.39,"price_change_24h":0.281378,"price_change_percentage_24h":6.34139,"market_cap_change_24h":345782861,"market_cap_change_percentage_24h":7.13246,"circulating_supply":1094303023.29452,"total_supply":1183246170.6779,"max_supply":null,"ath":20.44,"ath_change_percentage":-76.77039,"ath_date":"2022-01-16T22:09:45.873Z","atl":0.526762,"atl_change_percentage":801.29731,"atl_date":"2020-11-04T16:09:15.137Z","roi":null,"last_updated":"2024-07-07T01:27:43.139Z"},{"id":"litecoin","symbol":"ltc","name":"Litecoin","image":"https://coin-images.coingecko.com/coins/images/2/large/litecoin.png?1696501400","current_price":64.79,"market_cap":4864261727,"market_cap_rank":23,"fully_diluted_valuation":5468220443,"total_volume":260556709,"high_24h":65.58,"low_24h":61.58,"price_change_24h":2.56,"price_change_percentage_24h":4.11578,"market_cap_change_24h":217336636,"market_cap_change_percentage_24h":4.677,"circulating_supply":74722295.7334713,"total_supply":84000000.0,"max_supply":84000000.0,"ath":410.26,"ath_change_percentage":-84.11786,"ath_date":"2021-05-10T03:13:07.904Z","atl":1.15,"atl_change_percentage":5571.62538,"atl_date":"2015-01-14T00:00:00.000Z","roi":null,"last_updated":"2024-07-07T01:27:38.658Z"},{"id":"matic-network","symbol":"matic","name":"Polygon","image":"https://coin-images.coingecko.com/coins/images/4713/large/polygon.png?1698233745","current_price":0.499414,"market_cap":4648078112,"market_cap_rank":24,"fully_diluted_valuation":5007116632,"total_volume":209736798,"high_24h":0.507913,"low_24h":0.466068,"price_change_24h":0.03022473,"price_change_percentage_24h":6.4419,"market_cap_change_24h":300838286,"market_cap_change_percentage_24h":6.92021,"circulating_supply":9282943566.203985,"total_supply":10000000000.0,"max_supply":10000000000.0,"ath":2.92,"ath_change_percentage":-82.82608,"ath_date":"2021-12-27T02:08:34.307Z","atl":0.00314376,"atl_change_percentage":15831.13654,"atl_date":"2019-05-10T00:00:00.000Z","roi":{"times":188.89143382451127,"currency":"usd","percentage":18889.143382451126},"last_updated":"2024-07-07T01:28:00.544Z"},{"id":"wrapped-eeth","symbol":"weeth","name":"Wrapped eETH","image":"https://coin-images.coingecko.com/coins/images/33033/large/weETH.png?1701438396","current_price":3168.93,"market_cap":4321320125,"market_cap_rank":25,"fully_diluted_valuation":4321320125,"total_volume":85104360,"high_24h":3201.69,"low_24h":3077.04,"price_change_24h":71.68,"price_change_percentage_24h":2.31444,"market_cap_change_24h":96692959,"market_cap_change_percentage_24h":2.28879,"circulating_supply":1361806.84462927,"total_supply":1361806.84462927,"max_supply":null,"ath":4196.87,"ath_change_percentage":-24.47825,"ath_date":"2024-03-13T08:29:59.938Z","atl":2231.18,"atl_change_percentage":42.05746,"atl_date":"2024-01-08T03:35:28.624Z","roi":null,"last_updated":"2024-07-07T01:27:21.776Z"},{"id":"kaspa","symbol":"kas","name":"Kaspa","image":"https://coin-images.coingecko.com/coins/images/25751/large/kaspa-icon-exchanges.png?1696524837","current_price":0.165767,"market_cap":4020132287,"market_cap_rank":26,"fully_diluted_valuation":4020135219,"total_volume":57261599,"high_24h":0.174832,"low_24h":0.16007,"price_change_24h":0.0028162,"price_change_percentage_24h":1.72826,"market_cap_change_24h":104207096,"market_cap_change_percentage_24h":2.66111,"circulating_supply":24123618311.2672,"total_supply":24123635907.7121,"max_supply":28704026601.0,"ath":0.197627,"ath_change_percentage":-15.94117,"ath_date":"2024-06-30T13:25:37.086Z","atl":0.00017105,"atl_change_percentage":97019.52024,"atl_date":"2022-05-26T14:42:59.316Z","roi":null,"last_updated":"2024-07-07T01:28:01.190Z"},{"id":"pepe","symbol":"pepe","name":"Pepe","image":"https://coin-images.coingecko.com/coins/images/29850/large/pepe-token.jpeg?1696528776","current_price":9.46e-06,"market_cap":4011647650,"market_cap_rank":27,"fully_diluted_valuation":4011647650,"total_volume":665047983,"high_24h":9.89e-06,"low_24h":8.75e-06,"price_change_24h":4.23345e-07,"price_change_percentage_24h":4.68361,"market_cap_change_24h":227920696,"market_cap_change_percentage_24h":6.02371,"circulating_supply":420690000000000.0,"total_supply":420690000000000.0,"max_supply":420690000000000.0,"ath":1.717e-05,"ath_change_percentage":-44.69211,"ath_date":"2024-05-27T08:30:07.709Z","atl":5.5142e-08,"atl_change_percentage":17117.68802,"atl_date":"2023-04-18T02:14:41.591Z","roi":null,"last_updated":"2024-07-07T01:27:31.188Z"},{"id":"ethena-usde","symbol":"usde","name":"Ethena USDe","image":"https://coin-images.coingecko.com/coins/images/33613/large/USDE.png?1716355685","current_price":0.997001,"market_cap":3484484879,"market_cap_rank":28,"fully_diluted_valuation":3484484879,"total_volume":63382674,"high_24h":1.002,"low_24h":0.997348,"price_change_24h":-0.001404329334217636,"price_change_percentage_24h":-0.14066,"market_cap_change_24h":-24757863.0850029,"market_cap_change_percentage_24h":-0.7055,"circulating_supply":3485312254.89708,"total_supply":3485312254.89708,"max_supply":null,"ath":1.032,"ath_change_percentage":-3.30376,"ath_date":"2023-12-20T15:38:34.596Z","atl":0.965354,"atl_change_percentage":3.38014,"atl_date":"2024-04-13T20:11:19.603Z","roi":null,"last_updated":"2024-07-07T01:27:39.978Z"},{"id":"internet-computer","symbol":"icp","name":"Internet Computer","image":"https://coin-images.coingecko.com/coins/images/14495/large/Internet_Computer_logo.png?1696514180","current_price":7.39,"market_cap":3469246804,"market_cap_rank":29,"fully_diluted_valuation":3874906873,"total_volume":102834464,"high_24h":7.63,"low_24h":6.71,"price_change_24h":0.5506,"price_change_percentage_24h":8.05315,"market_cap_change_24h":289495532,"market_cap_change_percentage_24h":9.10435,"circulating_supply":465998299.740354,"total_supply":520487620.624006,"max_supply":null,"ath":700.65,"ath_change_percentage":-98.93837,"ath_date":"2021-05-10T16:05:53.653Z","atl":2.87,"atl_change_percentage":159.62377,"atl_date":"2023-09-22T00:29:57.369Z","roi":null,"last_updated":"2024-07-07T01:28:00.593Z"},{"id":"ethereum-classic","symbol":"etc","name":"Ethereum Classic","image":"https://coin-images.coingecko.com/coins/images/453/large/ethereum-classic-logo.png?1696501717","current_price":20.97,"market_cap":3117731361,"market_cap_rank":30,"fully_diluted_valuation":4444110529,"total_volume":108794846,"high_24h":21.28,"low_24h":20.09,"price_change_24h":0.639361,"price_change_percentage_24h":3.14462,"market_cap_change_24h":112651179,"market_cap_change_percentage_24h":3.74869,"circulating_supply":147814954.992149,"total_supply":210700000.0,"max_supply":210700000.0,"ath":167.09,"ath_change_percentage":-87.37634,"ath_date":"2021-05-06T18:34:22.133Z","atl":0.615038,"atl_change_percentage":3329.42803,"atl_date":"2016-07-25T00:00:00.000Z","roi":{"times":45.602786689159664,"currency":"usd","percentage":4560.278668915967},"last_updated":"2024-07-07T01:27:47.534Z"},{"id":"renzo-restaked-eth","symbol":"ezeth","name":"Renzo Restaked ETH","image":"https://coin-images.coingecko.com/coins/images/34753/large/Ezeth_logo_circle.png?1713496404","current_price":3080.87,"market_cap":3078864806,"market_cap_rank":31,"fully_diluted_valuation":3088253265,"total_volume":101590074,"high_24h":3114.02,"low_24h":2992.72,"price_change_24h":71.04,"price_change_percentage_24h":2.36013,"market_cap_change_24h":78280073,"market_cap_change_percentage_24h":2.60883,"circulating_supply":996928.060599325,"total_supply":999968.017915635,"max_supply":null,"ath":4106.74,"ath_change_percentage":-24.90307,"ath_date":"2024-03-12T00:44:29.429Z","atl":2198.04,"atl_change_percentage":40.30854,"atl_date":"2024-01-26T08:09:59.848Z","roi":null,"last_updated":"2024-07-07T01:27:39.556Z"},{"id":"fetch-ai","symbol":"fet","name":"Artificial Superintelligence Alliance","image":"https://coin-images.coingecko.com/coins/images/5681/large/ASI.png?1719827289","current_price":1.2,"market_cap":3053269603,"market_cap_rank":32,"fully_diluted_valuation":3185930270,"total_volume":179489517,"high_24h":1.28,"low_24h":1.15,"price_change_24h":0.03920461,"price_change_percentage_24h":3.36673,"market_cap_change_24h":135865596,"market_cap_change_percentage_24h":4.65707,"circulating_supply":2521012371.0,"total_supply":2630547141.0,"max_supply":2630547141.0,"ath":3.45,"ath_change_percentage":-64.93699,"ath_date":"2024-03-28T17:21:18.050Z","atl":0.00816959,"atl_change_percentage":14724.8306,"atl_date":"2020-03-13T02:24:18.347Z","roi":{"times":12.883233554307958,"currency":"usd","percentage":1288.3233554307958},"last_updated":"2024-07-07T01:27:37.545Z"},{"id":"monero","symbol":"xmr","name":"Monero","image":"https://coin-images.coingecko.com/coins/images/69/large/monero_logo.png?1696501460","current_price":157.67,"market_cap":2924777016,"market_cap_rank":33,"fully_diluted_valuation":null,"total_volume":49058311,"high_24h":159.24,"low_24h":153.68,"price_change_24h":2.78,"price_change_percentage_24h":1.79405,"market_cap_change_24h":60250689,"market_cap_change_percentage_24h":2.10334,"circulating_supply":18445342.6021475,"total_supply":18444108.0,"max_supply":null,"ath":542.33,"ath_change_percentage":-70.63274,"ath_date":"2018-01-09T00:00:00.000Z","atl":0.216177,"atl_change_percentage":73574.07202,"atl_date":"2015-01-14T00:00:00.000Z","roi":null,"last_updated":"2024-07-07T01:27:36.979Z"},{"id":"aptos","symbol":"apt","name":"Aptos","image":"https://coin-images.coingecko.com/coins/images/26455/large/aptos_round.png?1696525528","current_price":5.87,"market_cap":2686776429,"market_cap_rank":34,"fully_diluted_valuation":6537358627,"total_volume":119976680,"high_24h":6.04,"low_24h":5.49,"price_change_24h":0.315233,"price_change_percentage_24h":5.67037,"market_cap_change_24h":165996251,"market_cap_change_percentage_24h":6.58511,"circulating_supply":453941195.338222,"total_supply":1104511844.59955,"max_supply":null,"ath":19.92,"ath_change_percentage":-70.40767,"ath_date":"2023-01-26T14:25:17.390Z","atl":3.08,"atl_change_percentage":91.40587,"atl_date":"2022-12-29T21:35:14.796Z","roi":null,"last_updated":"2024-07-07T01:27:39.606Z"},{"id":"render-token","symbol":"rndr","name":"Render","image":"https://coin-images.coingecko.com/coins/images/11636/large/rndr.png?1696511529","current_price":6.84,"market_cap":2672501354,"market_cap_rank":35,"fully_diluted_valuation":3658757145,"total_volume":131888752,"high_24h":7.05,"low_24h":6.36,"price_change_24h":0.394866,"price_change_percentage_24h":6.12231,"market_cap_change_24h":172571556,"market_cap_change_percentage_24h":6.90306,"circulating_supply":388650384.455492,"total_supply":532077324.735492,"max_supply":532077324.735492,"ath":13.53,"ath_change_percentage":-49.13464,"ath_date":"2024-03-17T16:30:24.636Z","atl":0.03665669,"atl_change_percentage":18680.9386,"atl_date":"2020-06-16T13:22:25.900Z","roi":null,"last_updated":"2024-07-07T01:27:34.080Z"},{"id":"stellar","symbol":"xlm","name":"Stellar","image":"https://coin-images.coingecko.com/coins/images/100/large/Stellar_symbol_black_RGB.png?1696501482","current_price":0.089897,"market_cap":2629494303,"market_cap_rank":36,"fully_diluted_valuation":4504839554,"total_volume":47195236,"high_24h":0.090891,"low_24h":0.085288,"price_change_24h":0.00372873,"price_change_percentage_24h":4.32728,"market_cap_change_24h":117916571,"market_cap_change_percentage_24h":4.69492,"circulating_supply":29186258996.1966,"total_supply":50001786967.3715,"max_supply":50001786967.3715,"ath":0.875563,"ath_change_percentage":-89.68342,"ath_date":"2018-01-03T00:00:00.000Z","atl":0.00047612,"atl_change_percentage":18871.58597,"atl_date":"2015-03-05T00:00:00.000Z","roi":null,"last_updated":"2024-07-07T01:27:58.884Z"},{"id":"hedera-hashgraph","symbol":"hbar","name":"Hedera","image":"https://coin-images.coingecko.com/coins/images/3688/large/hbar.png?1696504364","current_price":0.068994,"market_cap":2479664101,"market_cap_rank":37,"fully_diluted_valuation":3465043293,"total_volume":43885735,"high_24h":0.070876,"low_24h":0.066377,"price_change_24h":0.00176055,"price_change_percentage_24h":2.61855,"market_cap_change_24h":78158465,"market_cap_change_percentage_24h":3.25456,"circulating_supply":35781141694.6665,"total_supply":50000000000.0,"max_supply":50000000000.0,"ath":0.569229,"ath_change_percentage":-87.81322,"ath_date":"2021-09-15T10:40:28.318Z","atl":0.00986111,"atl_change_percentage":603.47717,"atl_date":"2020-01-02T17:30:24.852Z","roi":null,"last_updated":"2024-07-07T01:27:54.951Z"},{"id":"cosmos","symbol":"atom","name":"Cosmos Hub","image":"https://coin-images.coingecko.com/coins/images/1481/large/cosmos_hub.png?1696502525","current_price":6.04,"market_cap":2366869378,"market_cap_rank":38,"fully_diluted_valuation":2368333435,"total_volume":126751960,"high_24h":6.14,"low_24h":5.71,"price_change_24h":0.270108,"price_change_percentage_24h":4.68536,"market_cap_change_24h":117439095,"market_cap_change_percentage_24h":5.22084,"circulating_supply":390688369.813272,"total_supply":390930035.085365,"max_supply":null,"ath":44.45,"ath_change_percentage":-86.36229,"ath_date":"2022-01-17T00:34:41.497Z","atl":1.16,"atl_change_percentage":422.53334,"atl_date":"2020-03-13T02:27:44.591Z","roi":{"times":59.35039525229836,"currency":"usd","percentage":5935.039525229836},"last_updated":"2024-07-07T01:27:39.413Z"},{"id":"crypto-com-chain","symbol":"cro","name":"Cronos","image":"https://coin-images.coingecko.com/coins/images/7310/large/cro_token_logo.png?1696507599","current_price":0.086484,"market_cap":2324277403,"market_cap_rank":39,"fully_diluted_valuation":2604892851,"total_volume":7143767,"high_24h":0.087742,"low_24h":0.084052,"price_change_24h":0.00209259,"price_change_percentage_24h":2.47961,"market_cap_change_24h":68128577,"market_cap_change_percentage_24h":3.01968,"circulating_supply":26768211235.7829,"total_supply":30000000000.0,"max_supply":null,"ath":0.965407,"ath_change_percentage":-91.00704,"ath_date":"2021-11-24T15:53:54.855Z","atl":0.0121196,"atl_change_percentage":616.34923,"atl_date":"2019-02-08T00:00:00.000Z","roi":null,"last_updated":"2024-07-07T01:27:59.394Z"},{"id":"okb","symbol":"okb","name":"OKB","image":"https://coin-images.coingecko.com/coins/images/4463/large/WeChat_Image_20220118095654.png?1696505053","current_price":37.68,"market_cap":2264900090,"market_cap_rank":40,"fully_diluted_valuation":8907009711,"total_volume":4015406,"high_24h":38.01,"low_24h":35.67,"price_change_24h":1.6,"price_change_percentage_24h":4.4348,"market_cap_change_24h":93752342,"market_cap_change_percentage_24h":4.3181,"circulating_supply":60000000.0,"total_supply":235957685.3,"max_supply":300000000.0,"ath":73.8,"ath_change_percentage":-48.85156,"ath_date":"2024-03-14T00:30:12.502Z","atl":0.580608,"atl_change_percentage":6401.67689,"atl_date":"2019-01-14T00:00:00.000Z","roi":null,"last_updated":"2024-07-07T01:27:36.770Z"},{"id":"filecoin","symbol":"fil","name":"Filecoin","image":"https://coin-images.coingecko.com/coins/images/12817/large/filecoin.png?1696512609","current_price":3.89,"market_cap":2223321012,"market_cap_rank":41,"fully_diluted_valuation":7675128280,"total_volume":146938014,"high_24h":4.0,"low_24h":3.52,"price_change_24h":0.329504,"price_change_percentage_24h":9.25328,"market_cap_change_24h":199878288,"market_cap_change_percentage_24h":9.87813,"circulating_supply":567815058.0,"total_supply":1960154825.0,"max_supply":1960154825.0,"ath":236.84,"ath_change_percentage":-98.34801,"ath_date":"2021-04-01T13:29:41.564Z","atl":2.64,"atl_change_percentage":48.14916,"atl_date":"2022-12-16T22:45:28.552Z","roi":null,"last_updated":"2024-07-07T01:27:38.956Z"},{"id":"arbitrum","symbol":"arb","name":"Arbitrum","image":"https://coin-images.coingecko.com/coins/images/16547/large/photo_2023-03-29_21.47.00.jpeg?1696516109","current_price":0.681957,"market_cap":2212784920,"market_cap_rank":42,"fully_diluted_valuation":6847360620,"total_volume":192083848,"high_24h":0.696694,"low_24h":0.615702,"price_change_24h":0.058953,"price_change_percentage_24h":9.46278,"market_cap_change_24h":203075610,"market_cap_change_percentage_24h":10.10473,"circulating_supply":3231588116.0,"total_supply":10000000000.0,"max_supply":10000000000.0,"ath":2.39,"ath_change_percentage":-71.41433,"ath_date":"2024-01-12T12:29:59.231Z","atl":0.581189,"atl_change_percentage":17.56575,"atl_date":"2024-07-05T04:21:51.979Z","roi":null,"last_updated":"2024-07-07T01:27:59.853Z"},{"id":"maker","symbol":"mkr","name":"Maker","image":"https://coin-images.coingecko.com/coins/images/1364/large/Mark_Maker.png?1696502423","current_price":2322.0,"market_cap":2169876912,"market_cap_rank":43,"fully_diluted_valuation":2280620496,"total_volume":74320155,"high_24h":2351.15,"low_24h":2215.94,"price_change_24h":87.06,"price_change_percentage_24h":3.89522,"market_cap_change_24h":95002519,"market_cap_change_percentage_24h":4.57871,"circulating_supply":930158.708716684,"total_supply":977631.036950888,"max_supply":1005577.0,"ath":6292.31,"ath_change_percentage":-62.90386,"ath_date":"2021-05-03T21:54:29.333Z","atl":168.36,"atl_change_percentage":1286.4573,"atl_date":"2020-03-16T20:52:36.527Z","roi":null,"last_updated":"2024-07-07T01:28:00.633Z"},{"id":"mantle","symbol":"mnt","name":"Mantle","image":"https://coin-images.coingecko.com/coins/images/30980/large/token-logo.png?1696529819","current_price":0.66076,"market_cap":2164380972,"market_cap_rank":44,"fully_diluted_valuation":4120484594,"total_volume":200557917,"high_24h":0.671075,"low_24h":0.634613,"price_change_24h":0.02177596,"price_change_percentage_24h":3.4079,"market_cap_change_24h":85249889,"market_cap_change_percentage_24h":4.10027,"circulating_supply":3266841707.83684,"total_supply":6219316794.99,"max_supply":6219316794.99,"ath":1.54,"ath_change_percentage":-57.04865,"ath_date":"2024-04-08T09:45:25.482Z","atl":0.307978,"atl_change_percentage":114.59298,"atl_date":"2023-10-18T02:50:46.942Z","roi":null,"last_updated":"2024-07-07T01:27:37.792Z"},{"id":"blockstack","symbol":"stx","name":"Stacks","image":"https://coin-images.coingecko.com/coins/images/2069/large/Stacks_Logo_png.png?1709979332","current_price":1.46,"market_cap":2133816796,"market_cap_rank":45,"fully_diluted_valuation":2638803321,"total_volume":52115957,"high_24h":1.51,"low_24h":1.37,"price_change_24h":0.067855,"price_change_percentage_24h":4.87881,"market_cap_change_24h":93237896,"market_cap_change_percentage_24h":4.56919,"circulating_supply":1470090212.80993,"total_supply":1818000000.0,"max_supply":1818000000.0,"ath":3.86,"ath_change_percentage":-62.43877,"ath_date":"2024-04-01T12:34:58.342Z","atl":0.04559639,"atl_change_percentage":3083.33732,"atl_date":"2020-03-13T02:29:26.415Z","roi":{"times":11.155546193330066,"currency":"usd","percentage":1115.5546193330067},"last_updated":"2024-07-07T01:27:35.574Z"},{"id":"immutable-x","symbol":"imx","name":"Immutable","image":"https://coin-images.coingecko.com/coins/images/17233/large/immutableX-symbol-BLK-RGB.png?1696516787","current_price":1.29,"market_cap":1956805545,"market_cap_rank":46,"fully_diluted_valuation":2595446943,"total_volume":51594421,"high_24h":1.35,"low_24h":1.25,"price_change_24h":0.00596465,"price_change_percentage_24h":0.46495,"market_cap_change_24h":24557286,"market_cap_change_percentage_24h":1.27092,"circulating_supply":1507875589.3898141,"total_supply":2000000000.0,"max_supply":2000000000.0,"ath":9.52,"ath_change_percentage":-86.37744,"ath_date":"2021-11-26T01:03:01.536Z","atl":0.378055,"atl_change_percentage":243.03472,"atl_date":"2022-12-31T07:36:37.649Z","roi":null,"last_updated":"2024-07-07T01:27:59.385Z"},{"id":"vechain","symbol":"vet","name":"VeChain","image":"https://coin-images.coingecko.com/coins/images/1167/large/VET_Token_Icon.png?1710013505","current_price":0.02402388,"market_cap":1952962618,"market_cap_rank":47,"fully_diluted_valuation":2073538134,"total_volume":46891059,"high_24h":0.0248635,"low_24h":0.02318056,"price_change_24h":0.00051049,"price_change_percentage_24h":2.17108,"market_cap_change_24h":51277443,"market_cap_change_percentage_24h":2.69642,"circulating_supply":80985041177.0,"total_supply":85985041177.0,"max_supply":86712634466.0,"ath":0.280991,"ath_change_percentage":-91.40547,"ath_date":"2021-04-19T01:08:21.675Z","atl":0.00191713,"atl_change_percentage":1159.6859,"atl_date":"2020-03-13T02:29:59.652Z","roi":{"times":1.765373826722776,"currency":"eth","percentage":176.5373826722776},"last_updated":"2024-07-07T01:27:31.475Z"},{"id":"injective-protocol","symbol":"inj","name":"Injective","image":"https://coin-images.coingecko.com/coins/images/12882/large/Secondary_Symbol.png?1696512670","current_price":19.66,"market_cap":1922871404,"market_cap_rank":48,"fully_diluted_valuation":1979235635,"total_volume":95776785,"high_24h":20.39,"low_24h":18.67,"price_change_24h":0.731737,"price_change_percentage_24h":3.86605,"market_cap_change_24h":90660478,"market_cap_change_percentage_24h":4.94815,"circulating_supply":97152222.33,"total_supply":100000000.0,"max_supply":null,"ath":52.62,"ath_change_percentage":-62.38673,"ath_date":"2024-03-14T15:06:22.124Z","atl":0.657401,"atl_change_percentage":2910.69839,"atl_date":"2020-11-03T16:19:30.576Z","roi":null,"last_updated":"2024-07-07T01:27:38.266Z"},{"id":"first-digital-usd","symbol":"fdusd","name":"First Digital USD","image":"https://coin-images.coingecko.com/coins/images/31079/large/firstfigital.jpeg?1696529912","current_price":1.0,"market_cap":1917843381,"market_cap_rank":49,"fully_diluted_valuation":1917843381,"total_volume":3059229866,"high_24h":1.006,"low_24h":0.995744,"price_change_24h":0.00033866,"price_change_percentage_24h":0.03386,"market_cap_change_24h":2464216,"market_cap_change_percentage_24h":0.12865,"circulating_supply":1915640773.91,"total_supply":1915640773.91,"max_supply":null,"ath":1.089,"ath_change_percentage":-8.02598,"ath_date":"2024-05-20T19:42:15.377Z","atl":0.942129,"atl_change_percentage":6.26856,"atl_date":"2023-08-17T21:55:41.478Z","roi":null,"last_updated":"2024-07-07T01:27:42.931Z"},{"id":"dogwifcoin","symbol":"wif","name":"dogwifhat","image":"https://coin-images.coingecko.com/coins/images/33566/large/dogwifhat.jpg?1702499428","current_price":1.86,"market_cap":1895929315,"market_cap_rank":50,"fully_diluted_valuation":1895929315,"total_volume":584939006,"high_24h":2.05,"low_24h":1.88,"price_change_24h":-0.09986758719948631,"price_change_percentage_24h":-5.1057,"market_cap_change_24h":-47279210.28889346,"market_cap_change_percentage_24h":-2.43305,"circulating_supply":998926392.0,"total_supply":998926392.0,"max_supply":998926392.0,"ath":4.83,"ath_change_percentage":-61.20567,"ath_date":"2024-03-31T09:34:58.366Z","atl":0.00155464,"atl_change_percentage":120314.11333,"atl_date":"2023-12-13T07:13:50.873Z","roi":null,"last_updated":"2024-07-07T01:27:31.165Z"},{"id":"the-graph","symbol":"grt","name":"The Graph","image":"https://coin-images.coingecko.com/coins/images/13397/large/Graph_Token.png?1696513159","current_price":0.18368,"market_cap":1758051528,"market_cap_rank":51,"fully_diluted_valuation":1986260135,"total_volume":48618711,"high_24h":0.188316,"low_24h":0.172445,"price_change_24h":0.00868345,"price_change_percentage_24h":4.96208,"market_cap_change_24h":91192696,"market_cap_change_percentage_24h":5.47093,"circulating_supply":9548531509.16547,"total_supply":10788004319.0,"max_supply":10788004319.0,"ath":2.84,"ath_change_percentage":-93.5121,"ath_date":"2021-02-12T07:28:45.775Z","atl":0.052051,"atl_change_percentage":254.17959,"atl_date":"2022-11-22T10:05:03.503Z","roi":null,"last_updated":"2024-07-07T01:27:53.122Z"},{"id":"rocket-pool-eth","symbol":"reth","name":"Rocket Pool ETH","image":"https://coin-images.coingecko.com/coins/images/20764/large/reth.png?1696520159","current_price":3404.12,"market_cap":1709708763,"market_cap_rank":52,"fully_diluted_valuation":1709708763,"total_volume":17382973,"high_24h":3435.26,"low_24h":3302.72,"price_change_24h":81.29,"price_change_percentage_24h":2.44631,"market_cap_change_24h":43013442,"market_cap_change_percentage_24h":2.58076,"circulating_supply":501717.00250807,"total_supply":501717.00250807,"max_supply":null,"ath":4814.31,"ath_change_percentage":-29.21693,"ath_date":"2021-12-01T08:03:50.749Z","atl":887.26,"atl_change_percentage":284.0704,"atl_date":"2022-06-18T20:55:45.957Z","roi":null,"last_updated":"2024-07-07T01:25:19.270Z"},{"id":"sui","symbol":"sui","name":"Sui","image":"https://coin-images.coingecko.com/coins/images/26375/large/sui_asset.jpeg?1696525453","current_price":0.675772,"market_cap":1701206705,"market_cap_rank":53,"fully_diluted_valuation":6771757610,"total_volume":96587682,"high_24h":0.69963,"low_24h":0.642992,"price_change_24h":0.02531078,"price_change_percentage_24h":3.89121,"market_cap_change_24h":70144073,"market_cap_change_percentage_24h":4.30051,"circulating_supply":2512208503.68389,"total_supply":10000000000.0,"max_supply":10000000000.0,"ath":2.17,"ath_change_percentage":-68.82693,"ath_date":"2024-03-27T17:46:02.608Z","atl":0.364846,"atl_change_percentage":85.49948,"atl_date":"2023-10-19T10:40:30.078Z","roi":null,"last_updated":"2024-07-07T01:27:33.132Z"},{"id":"optimism","symbol":"op","name":"Optimism","image":"https://coin-images.coingecko.com/coins/images/25244/large/Optimism.png?1696524385","current_price":1.45,"market_cap":1639319971,"market_cap_rank":54,"fully_diluted_valuation":6276764308,"total_volume":188092480,"high_24h":1.5,"low_24h":1.32,"price_change_24h":0.11626,"price_change_percentage_24h":8.71023,"market_cap_change_24h":144651941,"market_cap_change_percentage_24h":9.67786,"circulating_supply":1121728540.0,"total_supply":4294967296.0,"max_supply":4294967296.0,"ath":4.84,"ath_change_percentage":-69.9955,"ath_date":"2024-03-06T08:35:50.817Z","atl":0.402159,"atl_change_percentage":261.42681,"atl_date":"2022-06-18T20:54:52.178Z","roi":null,"last_updated":"2024-07-07T01:28:01.230Z"},{"id":"bittensor","symbol":"tao","name":"Bittensor","image":"https://coin-images.coingecko.com/coins/images/28452/large/ARUsPeNQ_400x400.jpeg?1696527447","current_price":225.18,"market_cap":1589998983,"market_cap_rank":55,"fully_diluted_valuation":4759528028,"total_volume":30387424,"high_24h":232.57,"low_24h":220.23,"price_change_24h":3.17,"price_change_percentage_24h":1.42631,"market_cap_change_24h":35178099,"market_cap_change_percentage_24h":2.26252,"circulating_supply":7015397.0,"total_supply":21000000.0,"max_supply":21000000.0,"ath":757.6,"ath_change_percentage":-70.23169,"ath_date":"2024-03-07T18:45:36.466Z","atl":30.83,"atl_change_percentage":631.51597,"atl_date":"2023-05-14T08:57:53.732Z","roi":null,"last_updated":"2024-07-07T01:27:39.225Z"},{"id":"arweave","symbol":"ar","name":"Arweave","image":"https://coin-images.coingecko.com/coins/images/4343/large/oRt6SiEN_400x400.jpg?1696504946","current_price":23.36,"market_cap":1540808141,"market_cap_rank":56,"fully_diluted_valuation":1540808141,"total_volume":64232900,"high_24h":24.12,"low_24h":21.67,"price_change_24h":1.15,"price_change_percentage_24h":5.16048,"market_cap_change_24h":90866408,"market_cap_change_percentage_24h":6.2669,"circulating_supply":65454185.5381511,"total_supply":65454185.5381511,"max_supply":66000000.0,"ath":89.24,"ath_change_percentage":-73.62817,"ath_date":"2021-11-05T04:14:42.689Z","atl":0.298788,"atl_change_percentage":7776.13868,"atl_date":"2020-01-31T06:47:36.543Z","roi":{"times":30.565396143971,"currency":"usd","percentage":3056.5396143971},"last_updated":"2024-07-07T01:27:22.732Z"},{"id":"mantle-staked-ether","symbol":"meth","name":"Mantle Staked Ether","image":"https://coin-images.coingecko.com/coins/images/33345/large/symbol_transparent_bg.png?1701697066","current_price":3153.99,"market_cap":1507981108,"market_cap_rank":57,"fully_diluted_valuation":1507981108,"total_volume":9508892,"high_24h":3197.62,"low_24h":3066.11,"price_change_24h":61.82,"price_change_percentage_24h":1.99925,"market_cap_change_24h":37300576,"market_cap_change_percentage_24h":2.53628,"circulating_supply":476032.061008447,"total_supply":476032.061008447,"max_supply":null,"ath":4729.53,"ath_change_percentage":-33.29754,"ath_date":"2024-03-27T05:26:27.333Z","atl":2142.02,"atl_change_percentage":47.27765,"atl_date":"2023-12-18T10:41:32.686Z","roi":null,"last_updated":"2024-07-07T01:27:19.990Z"},{"id":"bonk","symbol":"bonk","name":"Bonk","image":"https://coin-images.coingecko.com/coins/images/28600/large/bonk.jpg?1696527587","current_price":2.239e-05,"market_cap":1502308669,"market_cap_rank":58,"fully_diluted_valuation":2119376819,"total_volume":296081542,"high_24h":2.37e-05,"low_24h":2.143e-05,"price_change_24h":3.43309e-07,"price_change_percentage_24h":1.55732,"market_cap_change_24h":48736550,"market_cap_change_percentage_24h":3.35288,"circulating_supply":66295523592414.664,"total_supply":93526183276778.0,"max_supply":93526183276778.0,"ath":4.547e-05,"ath_change_percentage":-50.55999,"ath_date":"2024-03-04T17:05:29.594Z","atl":8.6142e-08,"atl_change_percentage":25997.2339,"atl_date":"2022-12-29T22:48:46.755Z","roi":null,"last_updated":"2024-07-07T01:27:29.412Z"},{"id":"bitget-token","symbol":"bgb","name":"Bitget Token","image":"https://coin-images.coingecko.com/coins/images/11610/large/icon_colour.png?1696511504","current_price":1.051,"market_cap":1470432451,"market_cap_rank":59,"fully_diluted_valuation":2100616287,"total_volume":50699143,"high_24h":1.058,"low_24h":1.017,"price_change_24h":0.01935305,"price_change_percentage_24h":1.87564,"market_cap_change_24h":27049597,"market_cap_change_percentage_24h":1.87404,"circulating_supply":1400001000.0,"total_supply":2000000000.0,"max_supply":2000000000.0,"ath":1.48,"ath_change_percentage":-28.9574,"ath_date":"2024-06-01T03:50:55.951Z","atl":0.0142795,"atl_change_percentage":7259.52367,"atl_date":"2020-06-25T04:17:05.895Z","roi":null,"last_updated":"2024-07-07T01:27:42.077Z"},{"id":"ondo-finance","symbol":"ondo","name":"Ondo","image":"https://coin-images.coingecko.com/coins/images/26580/large/ONDO.png?1696525656","current_price":1.012,"market_cap":1460714101,"market_cap_rank":60,"fully_diluted_valuation":10117397057,"total_volume":173330726,"high_24h":1.05,"low_24h":0.965059,"price_change_24h":0.01815158,"price_change_percentage_24h":1.82703,"market_cap_change_24h":29050735,"market_cap_change_percentage_24h":2.02916,"circulating_supply":1443764727.588207,"total_supply":10000000000.0,"max_supply":10000000000.0,"ath":1.48,"ath_change_percentage":-31.33679,"ath_date":"2024-06-03T08:29:55.744Z","atl":0.082171,"atl_change_percentage":1135.66752,"atl_date":"2024-01-18T12:14:30.524Z","roi":null,"last_updated":"2024-07-07T01:27:31.447Z"},{"id":"floki","symbol":"floki","name":"FLOKI","image":"https://coin-images.coingecko.com/coins/images/16746/large/PNG_image.png?1696516318","current_price":0.00014781,"market_cap":1442319038,"market_cap_rank":61,"fully_diluted_valuation":1488106912,"total_volume":232063409,"high_24h":0.00015441,"low_24h":0.00013704,"price_change_24h":7.95e-06,"price_change_percentage_24h":5.6847,"market_cap_change_24h":90749567,"market_cap_change_percentage_24h":6.71438,"circulating_supply":9692307903761.0,"total_supply":10000000000000.0,"max_supply":10000000000000.0,"ath":0.00034495,"ath_change_percentage":-56.94471,"ath_date":"2024-06-05T07:25:59.137Z","atl":8.428e-08,"atl_change_percentage":176121.27465,"atl_date":"2021-07-06T01:11:20.438Z","roi":null,"last_updated":"2024-07-07T01:27:55.043Z"},{"id":"lido-dao","symbol":"ldo","name":"Lido DAO","image":"https://coin-images.coingecko.com/coins/images/13573/large/Lido_DAO.png?1696513326","current_price":1.6,"market_cap":1442241456,"market_cap_rank":62,"fully_diluted_valuation":1615244417,"total_volume":146464453,"high_24h":1.65,"low_24h":1.54,"price_change_24h":0.0231272,"price_change_percentage_24h":1.46501,"market_cap_change_24h":34112844,"market_cap_change_percentage_24h":2.42257,"circulating_supply":892893633.418961,"total_supply":1000000000.0,"max_supply":1000000000.0,"ath":7.3,"ath_change_percentage":-77.88206,"ath_date":"2021-08-20T08:35:20.158Z","atl":0.40615,"atl_change_percentage":297.69676,"atl_date":"2022-06-18T20:55:12.035Z","roi":null,"last_updated":"2024-07-07T01:27:28.143Z"},{"id":"notcoin","symbol":"not","name":"Notcoin","image":"https://coin-images.coingecko.com/coins/images/33453/large/rFmThDiD_400x400.jpg?1701876350","current_price":0.01372444,"market_cap":1430033065,"market_cap_rank":63,"fully_diluted_valuation":1430033065,"total_volume":633827811,"high_24h":0.01412866,"low_24h":0.01004327,"price_change_24h":0.00341545,"price_change_percentage_24h":33.1308,"market_cap_change_24h":377948190,"market_cap_change_percentage_24h":35.92374,"circulating_supply":102491027711.698,"total_supply":102491027711.698,"max_supply":102719221714.0,"ath":0.02836145,"ath_change_percentage":-51.3204,"ath_date":"2024-06-02T18:00:38.587Z","atl":0.00461057,"atl_change_percentage":199.4479,"atl_date":"2024-05-24T07:12:14.147Z","roi":null,"last_updated":"2024-07-07T01:27:37.151Z"},{"id":"whitebit","symbol":"wbt","name":"WhiteBIT Coin","image":"https://coin-images.coingecko.com/coins/images/27045/large/wbt_token.png?1696526096","current_price":9.3,"market_cap":1341598052,"market_cap_rank":64,"fully_diluted_valuation":3258077750,"total_volume":4204537,"high_24h":9.35,"low_24h":9.25,"price_change_24h":0.02303954,"price_change_percentage_24h":0.24834,"market_cap_change_24h":5979267,"market_cap_change_percentage_24h":0.44768,"circulating_supply":144118517.10815412,"total_supply":349992558.0,"max_supply":400000000.0,"ath":14.64,"ath_change_percentage":-36.44066,"ath_date":"2022-10-28T12:32:18.119Z","atl":3.06,"atl_change_percentage":204.01325,"atl_date":"2023-02-13T19:01:21.899Z","roi":null,"last_updated":"2024-07-07T01:27:43.301Z"},{"id":"theta-token","symbol":"theta","name":"Theta Network","image":"https://coin-images.coingecko.com/coins/images/2538/large/theta-token-logo.png?1696503349","current_price":1.33,"market_cap":1333434123,"market_cap_rank":65,"fully_diluted_valuation":1333434123,"total_volume":13591152,"high_24h":1.37,"low_24h":1.26,"price_change_24h":0.04724306,"price_change_percentage_24h":3.68058,"market_cap_change_24h":53373490,"market_cap_change_percentage_24h":4.16961,"circulating_supply":1000000000.0,"total_supply":1000000000.0,"max_supply":1000000000.0,"ath":15.72,"ath_change_percentage":-91.48146,"ath_date":"2021-04-16T13:15:11.190Z","atl":0.04039979,"atl_change_percentage":3214.59615,"atl_date":"2020-03-13T02:24:16.483Z","roi":{"times":7.872128374380547,"currency":"usd","percentage":787.2128374380546},"last_updated":"2024-07-07T01:27:59.299Z"},{"id":"based-brett","symbol":"brett","name":"Brett","image":"https://coin-images.coingecko.com/coins/images/35529/large/1000050750.png?1709031995","current_price":0.127297,"market_cap":1276653637,"market_cap_rank":66,"fully_diluted_valuation":1276653637,"total_volume":56270602,"high_24h":0.131893,"low_24h":0.115911,"price_change_24h":0.00745717,"price_change_percentage_24h":6.22261,"market_cap_change_24h":84525230,"market_cap_change_percentage_24h":7.09028,"circulating_supply":9910198565.29341,"total_supply":9910198565.29341,"max_supply":9999998988.0,"ath":0.193328,"ath_change_percentage":-34.13813,"ath_date":"2024-06-09T12:55:51.835Z","atl":0.00084753,"atl_change_percentage":14923.62414,"atl_date":"2024-02-29T08:40:24.951Z","roi":null,"last_updated":"2024-07-07T01:27:48.025Z"},{"id":"fantom","symbol":"ftm","name":"Fantom","image":"https://coin-images.coingecko.com/coins/images/4001/large/Fantom_round.png?1696504642","current_price":0.44378,"market_cap":1253236944,"market_cap_rank":67,"fully_diluted_valuation":1419238785,"total_volume":157382349,"high_24h":0.462647,"low_24h":0.419284,"price_change_24h":0.01806497,"price_change_percentage_24h":4.24345,"market_cap_change_24h":61037586,"market_cap_change_percentage_24h":5.11975,"circulating_supply":2803634835.52659,"total_supply":3175000000.0,"max_supply":3175000000.0,"ath":3.46,"ath_change_percentage":-87.06543,"ath_date":"2021-10-28T05:19:39.845Z","atl":0.00190227,"atl_change_percentage":23416.72996,"atl_date":"2020-03-13T02:25:38.280Z","roi":{"times":13.79265248592954,"currency":"usd","percentage":1379.265248592954},"last_updated":"2024-07-07T01:27:33.312Z"},{"id":"aave","symbol":"aave","name":"Aave","image":"https://coin-images.coingecko.com/coins/images/12645/large/AAVE.png?1696512452","current_price":81.58,"market_cap":1222153425,"market_cap_rank":68,"fully_diluted_valuation":1315080071,"total_volume":97000853,"high_24h":83.44,"low_24h":78.65,"price_change_24h":1.99,"price_change_percentage_24h":2.50111,"market_cap_change_24h":42738679,"market_cap_change_percentage_24h":3.62372,"circulating_supply":14869402.431014985,"total_supply":16000000.0,"max_supply":16000000.0,"ath":661.69,"ath_change_percentage":-87.59065,"ath_date":"2021-05-18T21:19:59.514Z","atl":26.02,"atl_change_percentage":215.53241,"atl_date":"2020-11-05T09:20:11.928Z","roi":null,"last_updated":"2024-07-07T01:27:37.855Z"},{"id":"thorchain","symbol":"rune","name":"THORChain","image":"https://coin-images.coingecko.com/coins/images/6595/large/Rune200x200.png?1696506946","current_price":3.48,"market_cap":1173874345,"market_cap_rank":69,"fully_diluted_valuation":1442390866,"total_volume":144577640,"high_24h":3.57,"low_24h":3.31,"price_change_24h":0.129635,"price_change_percentage_24h":3.86679,"market_cap_change_24h":46133969,"market_cap_change_percentage_24h":4.09083,"circulating_supply":336453516.0,"total_supply":413415184.0,"max_supply":500000000.0,"ath":20.87,"ath_change_percentage":-83.23838,"ath_date":"2021-05-19T00:30:09.436Z","atl":0.00851264,"atl_change_percentage":40988.81669,"atl_date":"2019-09-28T00:00:00.000Z","roi":{"times":90.63598307584964,"currency":"usd","percentage":9063.598307584964},"last_updated":"2024-07-07T01:28:00.365Z"},{"id":"jasmycoin","symbol":"jasmy","name":"JasmyCoin","image":"https://coin-images.coingecko.com/coins/images/13876/large/JASMY200x200.jpg?1696513620","current_price":0.02403596,"market_cap":1173439458,"market_cap_rank":70,"fully_diluted_valuation":1211730130,"total_volume":167063772,"high_24h":0.02525781,"low_24h":0.02190031,"price_change_24h":0.00167991,"price_change_percentage_24h":7.51434,"market_cap_change_24h":102235256,"market_cap_change_percentage_24h":9.54396,"circulating_supply":48419999999.3058,"total_supply":50000000000.0,"max_supply":50000000000.0,"ath":4.79,"ath_change_percentage":-99.49407,"ath_date":"2021-02-16T03:53:32.207Z","atl":0.00275026,"atl_change_percentage":781.17358,"atl_date":"2022-12-29T20:41:09.113Z","roi":null,"last_updated":"2024-07-07T01:27:22.546Z"},{"id":"algorand","symbol":"algo","name":"Algorand","image":"https://coin-images.coingecko.com/coins/images/4380/large/download.png?1696504978","current_price":0.136922,"market_cap":1131399458,"market_cap_rank":71,"fully_diluted_valuation":1131399475,"total_volume":39055993,"high_24h":0.139185,"low_24h":0.129043,"price_change_24h":0.00551148,"price_change_percentage_24h":4.19411,"market_cap_change_24h":56359241,"market_cap_change_percentage_24h":5.24252,"circulating_supply":8206918001.32972,"total_supply":8206918122.26656,"max_supply":10000000000.0,"ath":3.56,"ath_change_percentage":-96.12919,"ath_date":"2019-06-20T14:51:19.480Z","atl":0.087513,"atl_change_percentage":57.51339,"atl_date":"2023-09-11T19:42:08.247Z","roi":{"times":-0.9429492862931288,"currency":"usd","percentage":-94.29492862931288},"last_updated":"2024-07-07T01:27:35.432Z"},{"id":"ether-fi-staked-eth","symbol":"eeth","name":"ether.fi Staked ETH","image":"https://coin-images.coingecko.com/coins/images/33049/large/ether.fi_eETH.png?1700473063","current_price":3046.36,"market_cap":1090161999,"market_cap_rank":72,"fully_diluted_valuation":5412794183,"total_volume":404584,"high_24h":3084.09,"low_24h":2951.22,"price_change_24h":73.61,"price_change_percentage_24h":2.47628,"market_cap_change_24h":8871063,"market_cap_change_percentage_24h":0.82041,"circulating_supply":357985.6538095203,"total_supply":1777444.69678337,"max_supply":null,"ath":15396.66,"ath_change_percentage":-80.21417,"ath_date":"2024-03-24T04:26:06.292Z","atl":2155.76,"atl_change_percentage":41.31263,"atl_date":"2024-02-08T11:26:30.368Z","roi":null,"last_updated":"2024-07-07T01:22:48.438Z"},{"id":"celestia","symbol":"tia","name":"Celestia","image":"https://coin-images.coingecko.com/coins/images/31967/large/tia.jpg?1696530772","current_price":5.47,"market_cap":1075516287,"market_cap_rank":73,"fully_diluted_valuation":5798075389,"total_volume":93159581,"high_24h":5.62,"low_24h":4.79,"price_change_24h":0.607283,"price_change_percentage_24h":12.49391,"market_cap_change_24h":128981599,"market_cap_change_percentage_24h":13.62672,"circulating_supply":195618870.215559,"total_supply":1054575342.46556,"max_supply":null,"ath":20.85,"ath_change_percentage":-73.73768,"ath_date":"2024-02-10T14:30:02.495Z","atl":2.08,"atl_change_percentage":162.82326,"atl_date":"2023-10-31T15:14:31.951Z","roi":null,"last_updated":"2024-07-07T01:27:30.946Z"},{"id":"quant-network","symbol":"qnt","name":"Quant","image":"https://coin-images.coingecko.com/coins/images/3370/large/5ZOu7brX_400x400.jpg?1696504070","current_price":73.34,"market_cap":1072246749,"market_cap_rank":74,"fully_diluted_valuation":1077283301,"total_volume":15863307,"high_24h":75.36,"low_24h":72.74,"price_change_24h":-0.7650771977331772,"price_change_percentage_24h":-1.03247,"market_cap_change_24h":-2581605.8354381323,"market_cap_change_percentage_24h":-0.24019,"circulating_supply":14544176.164091088,"total_supply":14612493.0,"max_supply":14612493.0,"ath":427.42,"ath_change_percentage":-82.72152,"ath_date":"2021-09-11T09:15:00.668Z","atl":0.215773,"atl_change_percentage":34126.69956,"atl_date":"2018-08-23T00:00:00.000Z","roi":{"times":9.3712835986721,"currency":"eth","percentage":937.12835986721},"last_updated":"2024-07-07T01:27:58.802Z"},{"id":"eos","symbol":"eos","name":"EOS","image":"https://coin-images.coingecko.com/coins/images/738/large/eos-eos-logo.png?1696501893","current_price":0.516348,"market_cap":1069422423,"market_cap_rank":75,"fully_diluted_valuation":null,"total_volume":85695356,"high_24h":0.525499,"low_24h":0.479234,"price_change_24h":0.0332006,"price_change_percentage_24h":6.87174,"market_cap_change_24h":75132892,"market_cap_change_percentage_24h":7.55644,"circulating_supply":2061210093.3808,"total_supply":null,"max_supply":null,"ath":22.71,"ath_change_percentage":-97.71452,"ath_date":"2018-04-29T07:50:33.540Z","atl":0.444515,"atl_change_percentage":16.77022,"atl_date":"2024-07-05T09:00:36.037Z","roi":{"times":-0.47843684485130816,"currency":"usd","percentage":-47.843684485130815},"last_updated":"2024-07-07T01:27:28.119Z"},{"id":"jupiter-exchange-solana","symbol":"jup","name":"Jupiter","image":"https://coin-images.coingecko.com/coins/images/34188/large/jup.png?1704266489","current_price":0.777559,"market_cap":1058211256,"market_cap_rank":76,"fully_diluted_valuation":7838601895,"total_volume":138574250,"high_24h":0.804298,"low_24h":0.733104,"price_change_24h":0.02430086,"price_change_percentage_24h":3.2261,"market_cap_change_24h":43504759,"market_cap_change_percentage_24h":4.28742,"circulating_supply":1350000000.0,"total_supply":10000000000.0,"max_supply":10000000000.0,"ath":2.0,"ath_change_percentage":-61.10556,"ath_date":"2024-01-31T15:02:47.304Z","atl":0.457464,"atl_change_percentage":70.04484,"atl_date":"2024-02-21T18:31:05.083Z","roi":null,"last_updated":"2024-07-07T01:27:31.748Z"},{"id":"pyth-network","symbol":"pyth","name":"Pyth Network","image":"https://coin-images.coingecko.com/coins/images/31924/large/pyth.png?1701245725","current_price":0.284034,"market_cap":1038434697,"market_cap_rank":77,"fully_diluted_valuation":2864656188,"total_volume":66916952,"high_24h":0.295185,"low_24h":0.264567,"price_change_24h":0.01377056,"price_change_percentage_24h":5.09523,"market_cap_change_24h":60677239,"market_cap_change_percentage_24h":6.20576,"circulating_supply":3624988931.64325,"total_supply":10000000000.0,"max_supply":10000000000.0,"ath":1.2,"ath_change_percentage":-76.14939,"ath_date":"2024-03-16T07:01:15.357Z","atl":0.228806,"atl_change_percentage":24.70862,"atl_date":"2024-01-08T03:29:54.594Z","roi":null,"last_updated":"2024-07-07T01:27:26.710Z"},{"id":"coredaoorg","symbol":"core","name":"Core","image":"https://coin-images.coingecko.com/coins/images/28938/large/file_589.jpg?1701868471","current_price":1.053,"market_cap":954634316,"market_cap_rank":78,"fully_diluted_valuation":2235316976,"total_volume":149113834,"high_24h":1.16,"low_24h":0.862066,"price_change_24h":0.178251,"price_change_percentage_24h":20.37378,"market_cap_change_24h":171642345,"market_cap_change_percentage_24h":21.92134,"circulating_supply":896844646.530532,"total_supply":2100000000.0,"max_supply":2100000000.0,"ath":6.14,"ath_change_percentage":-82.73244,"ath_date":"2023-02-08T12:55:39.828Z","atl":0.334237,"atl_change_percentage":217.39612,"atl_date":"2023-11-03T01:20:55.441Z","roi":null,"last_updated":"2024-07-07T01:27:38.531Z"},{"id":"elrond-erd-2","symbol":"egld","name":"MultiversX","image":"https://coin-images.coingecko.com/coins/images/12335/large/egld-token-logo.png?1696512162","current_price":34.36,"market_cap":938407243,"market_cap_rank":79,"fully_diluted_valuation":938585301,"total_volume":37113143,"high_24h":35.08,"low_24h":32.81,"price_change_24h":0.908412,"price_change_percentage_24h":2.71564,"market_cap_change_24h":31069660,"market_cap_change_percentage_24h":3.42427,"circulating_supply":27152303.0,"total_supply":27157455.0,"max_supply":31415926.0,"ath":545.64,"ath_change_percentage":-93.66792,"ath_date":"2021-11-23T10:33:26.737Z","atl":6.51,"atl_change_percentage":430.9993,"atl_date":"2020-10-07T01:44:53.554Z","roi":null,"last_updated":"2024-07-07T01:28:01.849Z"},{"id":"flare-networks","symbol":"flr","name":"Flare","image":"https://coin-images.coingecko.com/coins/images/28624/large/FLR-icon200x200.png?1696527609","current_price":0.02144539,"market_cap":930285482,"market_cap_rank":80,"fully_diluted_valuation":2212584859,"total_volume":12803537,"high_24h":0.02204847,"low_24h":0.02032605,"price_change_24h":0.0010973,"price_change_percentage_24h":5.39265,"market_cap_change_24h":47888777,"market_cap_change_percentage_24h":5.42713,"circulating_supply":43024854264.702,"total_supply":102330029803.04,"max_supply":null,"ath":0.150073,"ath_change_percentage":-85.65173,"ath_date":"2023-01-10T03:14:05.921Z","atl":0.00827405,"atl_change_percentage":160.24586,"atl_date":"2023-10-19T03:35:41.663Z","roi":null,"last_updated":"2024-07-07T01:27:37.586Z"},{"id":"gatechain-token","symbol":"gt","name":"Gate","image":"https://coin-images.coingecko.com/coins/images/8183/large/gate.png?1696508395","current_price":7.05,"market_cap":920487103,"market_cap_rank":81,"fully_diluted_valuation":2118346588,"total_volume":2417610,"high_24h":7.06,"low_24h":6.73,"price_change_24h":0.23386,"price_change_percentage_24h":3.43172,"market_cap_change_24h":30023552,"market_cap_change_percentage_24h":3.37168,"circulating_supply":130359277.55886991,"total_supply":300000000.0,"max_supply":null,"ath":12.94,"ath_change_percentage":-45.43943,"ath_date":"2021-05-12T11:39:16.531Z","atl":0.25754,"atl_change_percentage":2641.7668,"atl_date":"2020-03-13T02:18:02.481Z","roi":null,"last_updated":"2024-07-07T01:27:44.084Z"},{"id":"akash-network","symbol":"akt","name":"Akash Network","image":"https://coin-images.coingecko.com/coins/images/12785/large/akash-logo.png?1696512580","current_price":3.65,"market_cap":885711878,"market_cap_rank":82,"fully_diluted_valuation":890230951,"total_volume":21035618,"high_24h":3.8,"low_24h":3.22,"price_change_24h":0.343637,"price_change_percentage_24h":10.40055,"market_cap_change_24h":89610335,"market_cap_change_percentage_24h":11.25614,"circulating_supply":242000864.65392,"total_supply":243235599.648306,"max_supply":388539008.0,"ath":8.07,"ath_change_percentage":-54.62455,"ath_date":"2021-04-06T18:59:48.484Z","atl":0.164994,"atl_change_percentage":2120.7209,"atl_date":"2022-11-21T20:30:53.727Z","roi":null,"last_updated":"2024-07-07T01:27:29.426Z"},{"id":"kucoin-shares","symbol":"kcs","name":"KuCoin","image":"https://coin-images.coingecko.com/coins/images/1047/large/sa9z79.png?1696502152","current_price":9.15,"market_cap":876866994,"market_cap_rank":83,"fully_diluted_valuation":1312820182,"total_volume":99887,"high_24h":9.22,"low_24h":8.87,"price_change_24h":0.261556,"price_change_percentage_24h":2.94199,"market_cap_change_24h":28713321,"market_cap_change_percentage_24h":3.38539,"circulating_supply":95540492.2885607,"total_supply":143040492.288477,"max_supply":null,"ath":28.83,"ath_change_percentage":-68.19606,"ath_date":"2021-12-01T15:09:35.541Z","atl":0.342863,"atl_change_percentage":2574.25764,"atl_date":"2019-02-07T00:00:00.000Z","roi":null,"last_updated":"2024-07-07T01:27:20.498Z"},{"id":"sei-network","symbol":"sei","name":"Sei","image":"https://coin-images.coingecko.com/coins/images/28205/large/Sei_Logo_-_Transparent.png?1696527207","current_price":0.282076,"market_cap":860879631,"market_cap_rank":84,"fully_diluted_valuation":2822556166,"total_volume":55984750,"high_24h":0.29021,"low_24h":0.271386,"price_change_24h":0.00453297,"price_change_percentage_24h":1.63325,"market_cap_change_24h":16026755,"market_cap_change_percentage_24h":1.89699,"circulating_supply":3050000000.0,"total_supply":10000000000.0,"max_supply":null,"ath":1.14,"ath_change_percentage":-75.26761,"ath_date":"2024-03-16T02:30:23.904Z","atl":0.095364,"atl_change_percentage":195.5835,"atl_date":"2023-10-19T08:05:30.655Z","roi":null,"last_updated":"2024-07-07T01:27:33.038Z"},{"id":"kelp-dao-restaked-eth","symbol":"rseth","name":"Kelp DAO Restaked ETH","image":"https://coin-images.coingecko.com/coins/images/33800/large/Icon___Dark.png?1702991855","current_price":3084.83,"market_cap":834585853,"market_cap_rank":85,"fully_diluted_valuation":834585853,"total_volume":18052249,"high_24h":3111.95,"low_24h":2986.99,"price_change_24h":73.07,"price_change_percentage_24h":2.42632,"market_cap_change_24h":-24873596.064224362,"market_cap_change_percentage_24h":-2.8941,"circulating_supply":270238.26457048,"total_supply":270238.26457048,"max_supply":null,"ath":4033.48,"ath_change_percentage":-23.51929,"ath_date":"2024-03-13T08:55:33.936Z","atl":2069.62,"atl_change_percentage":49.05269,"atl_date":"2024-01-23T14:25:53.609Z","roi":null,"last_updated":"2024-07-07T01:25:55.127Z"},{"id":"flow","symbol":"flow","name":"Flow","image":"https://coin-images.coingecko.com/coins/images/13446/large/5f6294c0c7a8cda55cb1c936_Flow_Wordmark.png?1696513210","current_price":0.534202,"market_cap":813487345,"market_cap_rank":86,"fully_diluted_valuation":813487345,"total_volume":21470735,"high_24h":0.545513,"low_24h":0.503817,"price_change_24h":0.02383652,"price_change_percentage_24h":4.67048,"market_cap_change_24h":41131100,"market_cap_change_percentage_24h":5.32541,"circulating_supply":1517464468.62262,"total_supply":1517464468.62262,"max_supply":null,"ath":42.4,"ath_change_percentage":-98.73695,"ath_date":"2021-04-05T13:49:10.098Z","atl":0.391969,"atl_change_percentage":36.61746,"atl_date":"2023-09-11T19:41:06.528Z","roi":null,"last_updated":"2024-07-07T01:27:31.256Z"},{"id":"ethereum-name-service","symbol":"ens","name":"Ethereum Name Service","image":"https://coin-images.coingecko.com/coins/images/19785/large/acatxTm8_400x400.jpg?1696519207","current_price":25.26,"market_cap":804002220,"market_cap_rank":87,"fully_diluted_valuation":2540336776,"total_volume":229701487,"high_24h":26.63,"low_24h":22.59,"price_change_24h":2.26,"price_change_percentage_24h":9.82725,"market_cap_change_24h":74946712,"market_cap_change_percentage_24h":10.27997,"circulating_supply":31649434.352591332,"total_supply":100000000.0,"max_supply":100000000.0,"ath":83.4,"ath_change_percentage":-69.59521,"ath_date":"2021-11-11T02:20:01.099Z","atl":6.69,"atl_change_percentage":278.98644,"atl_date":"2023-10-19T02:35:00.861Z","roi":null,"last_updated":"2024-07-07T01:27:30.946Z"},{"id":"gala","symbol":"gala","name":"GALA","image":"https://coin-images.coingecko.com/coins/images/12493/large/GALA_token_image_-_200PNG.png?1709725869","current_price":0.021837,"market_cap":798712007,"market_cap_rank":88,"fully_diluted_valuation":798712011,"total_volume":72524137,"high_24h":0.02306898,"low_24h":0.02101438,"price_change_24h":0.00051001,"price_change_percentage_24h":2.3914,"market_cap_change_24h":25272892,"market_cap_change_percentage_24h":3.2676,"circulating_supply":36273089759.2917,"total_supply":36273089944.4682,"max_supply":50000000000.0,"ath":0.824837,"ath_change_percentage":-97.33264,"ath_date":"2021-11-26T01:03:48.731Z","atl":0.00013475,"atl_change_percentage":16227.61409,"atl_date":"2020-12-28T08:46:48.367Z","roi":null,"last_updated":"2024-07-07T01:27:40.198Z"},{"id":"zebec-protocol","symbol":"zbc","name":"Zebec Protocol","image":"https://coin-images.coingecko.com/coins/images/24342/large/zebec.jpeg?1696523526","current_price":0.01549565,"market_cap":790714792,"market_cap_rank":89,"fully_diluted_valuation":1553779539,"total_volume":13110.62,"high_24h":0.01780587,"low_24h":0.0154486,"price_change_24h":-0.001804210013996563,"price_change_percentage_24h":-10.42905,"market_cap_change_24h":-99642246.21299481,"market_cap_change_percentage_24h":-11.19127,"circulating_supply":50883649370.0,"total_supply":99987978070.0,"max_supply":10000000000.0,"ath":0.052766,"ath_change_percentage":-70.55004,"ath_date":"2022-04-13T15:54:52.330Z","atl":0.00570409,"atl_change_percentage":172.43015,"atl_date":"2023-10-20T04:02:48.815Z","roi":null,"last_updated":"2024-07-07T01:27:57.892Z"},{"id":"axie-infinity","symbol":"axs","name":"Axie Infinity","image":"https://coin-images.coingecko.com/coins/images/13029/large/axie_infinity_logo.png?1696512817","current_price":5.27,"market_cap":784401010,"market_cap_rank":90,"fully_diluted_valuation":1435017752,"total_volume":36213485,"high_24h":5.42,"low_24h":4.91,"price_change_24h":0.28699,"price_change_percentage_24h":5.7539,"market_cap_change_24h":49974658,"market_cap_change_percentage_24h":6.80458,"circulating_supply":147585820.83379,"total_supply":270000000.0,"max_supply":270000000.0,"ath":164.9,"ath_change_percentage":-96.77962,"ath_date":"2021-11-06T19:29:29.482Z","atl":0.123718,"atl_change_percentage":4192.28329,"atl_date":"2020-11-06T08:05:43.662Z","roi":null,"last_updated":"2024-07-07T01:27:31.074Z"},{"id":"dydx-chain","symbol":"dydx","name":"dYdX","image":"https://coin-images.coingecko.com/coins/images/32594/large/dydx.png?1698673495","current_price":1.29,"market_cap":784189720,"market_cap_rank":91,"fully_diluted_valuation":997480448,"total_volume":24866527,"high_24h":1.32,"low_24h":1.2,"price_change_24h":0.07408,"price_change_percentage_24h":6.09718,"market_cap_change_24h":47979215,"market_cap_change_percentage_24h":6.51705,"circulating_supply":606068271.4561341,"total_supply":770911981.0,"max_supply":1000000000.0,"ath":4.52,"ath_change_percentage":-71.44803,"ath_date":"2024-03-07T22:19:11.131Z","atl":1.022,"atl_change_percentage":26.19463,"atl_date":"2024-07-05T04:20:44.553Z","roi":null,"last_updated":"2024-07-07T01:27:33.795Z"},{"id":"msol","symbol":"msol","name":"Marinade Staked SOL","image":"https://coin-images.coingecko.com/coins/images/17752/large/mSOL.png?1696517278","current_price":169.17,"market_cap":768811594,"market_cap_rank":92,"fully_diluted_valuation":768824489,"total_volume":21680771,"high_24h":172.71,"low_24h":159.73,"price_change_24h":6.98,"price_change_percentage_24h":4.30121,"market_cap_change_24h":32601871,"market_cap_change_percentage_24h":4.42834,"circulating_supply":4531213.0,"total_supply":4531289.0,"max_supply":4531289.0,"ath":261.93,"ath_change_percentage":-35.26755,"ath_date":"2021-11-07T00:00:00.000Z","atl":8.93,"atl_change_percentage":1798.67843,"atl_date":"2022-12-29T20:45:33.039Z","roi":null,"last_updated":"2024-07-07T01:27:02.476Z"},{"id":"tokenize-xchange","symbol":"tkx","name":"Tokenize Xchange","image":"https://coin-images.coingecko.com/coins/images/4984/large/TKX_-_Logo_-_RGB-15.png?1696505519","current_price":9.56,"market_cap":765558622,"market_cap_rank":93,"fully_diluted_valuation":956996128,"total_volume":8694550,"high_24h":9.61,"low_24h":9.28,"price_change_24h":0.250204,"price_change_percentage_24h":2.68672,"market_cap_change_24h":19015310,"market_cap_change_percentage_24h":2.54711,"circulating_supply":79995999.94518414,"total_supply":100000000.0,"max_supply":100000000.0,"ath":22.3,"ath_change_percentage":-57.05524,"ath_date":"2022-10-31T10:23:59.455Z","atl":0.111255,"atl_change_percentage":8506.43526,"atl_date":"2019-04-28T00:00:00.000Z","roi":{"times":31.91851252599879,"currency":"usd","percentage":3191.851252599879},"last_updated":"2024-07-07T01:27:53.268Z"},{"id":"bittorrent","symbol":"btt","name":"BitTorrent","image":"https://coin-images.coingecko.com/coins/images/22457/large/btt_logo.png?1696521780","current_price":7.88558e-07,"market_cap":763785413,"market_cap_rank":94,"fully_diluted_valuation":780945363,"total_volume":22718616,"high_24h":7.95934e-07,"low_24h":7.47765e-07,"price_change_24h":3.6023e-08,"price_change_percentage_24h":4.78691,"market_cap_change_24h":34328807,"market_cap_change_percentage_24h":4.70608,"circulating_supply":968246428571000.0,"total_supply":990000000000000.0,"max_supply":990000000000000.0,"ath":3.43e-06,"ath_change_percentage":-77.06919,"ath_date":"2022-01-21T04:00:31.909Z","atl":3.65368e-07,"atl_change_percentage":115.35394,"atl_date":"2023-10-13T05:10:41.241Z","roi":null,"last_updated":"2024-07-07T01:27:49.909Z"},{"id":"mantra-dao","symbol":"om","name":"MANTRA","image":"https://coin-images.coingecko.com/coins/images/12151/large/OM_Token.png?1696511991","current_price":0.89448,"market_cap":750774956,"market_cap_rank":95,"fully_diluted_valuation":802761635,"total_volume":47267707,"high_24h":0.906267,"low_24h":0.805687,"price_change_24h":0.071145,"price_change_percentage_24h":8.64107,"market_cap_change_24h":68951932,"market_cap_change_percentage_24h":10.11288,"circulating_supply":831324626.4,"total_supply":888888888.0,"max_supply":888888888.0,"ath":1.093,"ath_change_percentage":-17.25398,"ath_date":"2024-06-10T02:21:19.458Z","atl":0.01726188,"atl_change_percentage":5141.74303,"atl_date":"2023-10-12T17:25:09.068Z","roi":null,"last_updated":"2024-07-07T01:28:00.610Z"},{"id":"beam-2","symbol":"beam","name":"Beam","image":"https://coin-images.coingecko.com/coins/images/32417/large/chain-logo.png?1698114384","current_price":0.01481063,"market_cap":750280722,"market_cap_rank":96,"fully_diluted_valuation":931115533,"total_volume":15553685,"high_24h":0.01524113,"low_24h":0.0139982,"price_change_24h":0.00060174,"price_change_percentage_24h":4.23497,"market_cap_change_24h":37063703,"market_cap_change_percentage_24h":5.19669,"circulating_supply":50308507573.0,"total_supply":62434008330.0,"max_supply":62434008330.0,"ath":0.04416304,"ath_change_percentage":-66.4229,"ath_date":"2024-03-10T10:40:22.381Z","atl":0.0043383,"atl_change_percentage":241.80808,"atl_date":"2023-10-29T08:20:14.064Z","roi":null,"last_updated":"2024-07-07T01:27:40.272Z"},{"id":"usdd","symbol":"usdd","name":"USDD","image":"https://coin-images.coingecko.com/coins/images/25380/large/UUSD.jpg?1696524513","current_price":0.997982,"market_cap":741881056,"market_cap_rank":97,"fully_diluted_valuation":null,"total_volume":2503542,"high_24h":1.009,"low_24h":0.993728,"price_change_24h":8.551e-05,"price_change_percentage_24h":0.00857,"market_cap_change_24h":7433264,"market_cap_change_percentage_24h":1.01209,"circulating_supply":740873347.234201,"total_supply":null,"max_supply":null,"ath":1.052,"ath_change_percentage":-5.0435,"ath_date":"2023-10-23T22:45:25.398Z","atl":0.928067,"atl_change_percentage":7.61837,"atl_date":"2022-06-19T16:15:11.558Z","roi":null,"last_updated":"2024-07-07T01:27:34.333Z"},{"id":"fasttoken","symbol":"ftn","name":"Fasttoken","image":"https://coin-images.coingecko.com/coins/images/28478/large/lightenicon_200x200.png?1696527472","current_price":2.32,"market_cap":741089677,"market_cap_rank":98,"fully_diluted_valuation":2042857391,"total_volume":14554930,"high_24h":2.33,"low_24h":2.31,"price_change_24h":-0.001708903137219053,"price_change_percentage_24h":-0.07364,"market_cap_change_24h":1396290,"market_cap_change_percentage_24h":0.18877,"circulating_supply":319238591.17373455,"total_supply":880000000.0,"max_supply":1000000000.0,"ath":2.33,"ath_change_percentage":-0.63553,"ath_date":"2024-07-06T14:45:16.468Z","atl":0.398142,"atl_change_percentage":482.6544,"atl_date":"2023-01-21T10:15:39.503Z","roi":null,"last_updated":"2024-07-07T01:27:47.990Z"},{"id":"starknet","symbol":"strk","name":"Starknet","image":"https://coin-images.coingecko.com/coins/images/26433/large/starknet.png?1696525507","current_price":0.557676,"market_cap":729342145,"market_cap_rank":99,"fully_diluted_valuation":5608978706,"total_volume":90566428,"high_24h":0.582885,"low_24h":0.503319,"price_change_24h":0.04277081,"price_change_percentage_24h":8.30654,"market_cap_change_24h":62198019,"market_cap_change_percentage_24h":9.32303,"circulating_supply":1300311845.0,"total_supply":10000000000.0,"max_supply":10000000000.0,"ath":4.41,"ath_change_percentage":-87.30013,"ath_date":"2024-02-20T12:05:13.556Z","atl":0.468272,"atl_change_percentage":19.70144,"atl_date":"2024-07-05T03:14:17.806Z","roi":null,"last_updated":"2024-07-07T01:27:32.698Z"},{"id":"tezos","symbol":"xtz","name":"Tezos","image":"https://coin-images.coingecko.com/coins/images/976/large/Tezos-logo.png?1696502091","current_price":0.733913,"market_cap":728699189,"market_cap_rank":100,"fully_diluted_valuation":743861398,"total_volume":24041187,"high_24h":0.754319,"low_24h":0.7175,"price_change_24h":0.00776373,"price_change_percentage_24h":1.06916,"market_cap_change_24h":10919923,"market_cap_change_percentage_24h":1.52135,"circulating_supply":988119565.996306,"total_supply":1008679592.81218,"max_supply":null,"ath":9.12,"ath_change_percentage":-91.89219,"ath_date":"2021-10-04T00:41:18.025Z","atl":0.350476,"atl_change_percentage":110.88837,"atl_date":"2018-12-07T00:00:00.000Z","roi":{"times":0.56151689831764,"currency":"usd","percentage":56.151689831764},"last_updated":"2024-07-07T01:27:55.514Z"}]