[{"id":"bitcoin","symbol":"btc","name":"Bitcoin","image":"https://coin-images.coingecko.com/coins/images/1/large/bitcoin.png?1696501400","current_price":77263,"market_cap":1530993095501,"market_cap_rank":1,"fully_diluted_valuation":1530994483884,"total_volume":63120085078,"high_24h":78373,"low_24h":74773,"price_change_24h":-1110.2916161877947,"price_change_percentage_24h":-1.41667,"market_cap_change_24h":-25712261701.649414,"market_cap_change_percentage_24h":-1.65171,"circulating_supply":19848903.0,"total_supply":19848921.0,"max_supply":21000000.0,"ath":108786,"ath_change_percentage":-29.09365,"ath_date":"2025-01-20T09:11:54.494Z","atl":67.81,"atl_change_percentage":113654.58098,"atl_date":"2013-07-06T00:00:00.000Z","roi":null,"last_updated":"2025-04-09T16:07:33.289Z"},{"id":"ethereum","symbol":"eth","name":"Ethereum","image":"https://coin-images.coingecko.com/coins/images/279/large/ethereum.png?1696501628","current_price":1486.09,"market_cap":179179238361,"market_cap_rank":2,"fully_diluted_valuation":179179238361,"total_volume":32952144696,"high_24h":1529.71,"low_24h":1398.62,"price_change_24h":-43.62513371484465,"price_change_percentage_24h":-2.85185,"market_cap_change_24h":-5537523881.419037,"market_cap_change_percentage_24h":-2.99785,"circulating_supply":120678504.3257155,"total_supply":120678504.3257155,"max_supply":null,"ath":4878.26,"ath_change_percentage":-69.54712,"ath_date":"2021-11-10T14:24:19.604Z","atl":0.432979,"atl_change_percentage":343004.68969,"atl_date":"2015-10-20T00:00:00.000Z","roi":{"times":24.701761031717076,"currency":"btc","percentage":2470.176103171708},"last_updated":"2025-04-09T16:07:28.290Z"},{"id":"tether","symbol":"usdt","name":"Tether","image":"https://coin-images.coingecko.com/coins/images/325/large/Tether.png?1696501661","current_price":0.999191,"market_cap":143899145956,"market_cap_rank":3,"fully_diluted_valuation":143899145956,"total_volume":47790824420,"high_24h":0.999615,"low_24h":0.998787,"price_change_24h":-0.00040171034997305,"price_change_percentage_24h":-0.04019,"market_cap_change_24h":-234369309.49682617,"market_cap_change_percentage_24h":-0.16261,"circulating_supply":144014397535.6818,"total_supply":144014397535.6818,"max_supply":null,"ath":1.32,"ath_change_percentage":-24.47977,"ath_date":"2018-07-24T00:00:00.000Z","atl":0.572521,"atl_change_percentage":74.52716,"atl_date":"2015-03-02T00:00:00.000Z","roi":null,"last_updated":"2025-04-09T16:07:28.307Z"},{"id":"ripple","symbol":"xrp","name":"XRP","image":"https://coin-images.coingecko.com/coins/images/44/large/xrp-symbol-white-128.png?1696501442","current_price":1.83,"market_cap":106594251415,"market_cap_rank":4,"fully_diluted_valuation":182890897618,"total_volume":6479027034,"high_24h":1.9,"low_24h":1.73,"price_change_24h":-0.07243253409949202,"price_change_percentage_24h":-3.80711,"market_cap_change_24h":-4333234024.590103,"market_cap_change_percentage_24h":-3.90637,"circulating_supply":58274974538.0,"total_supply":99986277500.0,"max_supply":100000000000.0,"ath":3.4,"ath_change_percentage":-46.03961,"ath_date":"2018-01-07T00:00:00.000Z","atl":0.00268621,"atl_change_percentage":68167.90221,"atl_date":"2014-05-22T00:00:00.000Z","roi":null,"last_updated":"2025-04-09T16:07:34.255Z"},{"id":"binancecoin","symbol":"bnb","name":"BNB","image":"https://coin-images.coingecko.com/coins/images/825/large/bnb-icon2_2x.png?1696501970","current_price":562.05,"market_cap":81915947344,"market_cap_rank":5,"fully_diluted_valuation":81915947344,"total_volume":1080083981,"high_24h":562.51,"low_24h":538.12,"price_change_24h":1.81,"price_change_percentage_24h":0.32229,"market_cap_change_24h":122936102,"market_cap_change_percentage_24h":0.1503,"circulating_supply":145887575.79,"total_supply":145887575.79,"max_supply":200000000.0,"ath":788.84,"ath_change_percentage":-28.8603,"ath_date":"2024-12-04T10:35:25.220Z","atl":0.0398177,"atl_change_percentage":1409275.83167,"atl_date":"2017-10-19T00:00:00.000Z","roi":null,"last_updated":"2025-04-09T16:07:35.504Z"},{"id":"usd-coin","symbol":"usdc","name":"USDC","image":"https://coin-images.coingecko.com/coins/images/6319/large/usdc.png?1696506694","current_price":0.999922,"market_cap":59980612547,"market_cap_rank":6,"fully_diluted_valuation":60034999537,"total_volume":20587494395,"high_24h":1.0,"low_24h":0.99978,"price_change_24h":3.511e-05,"price_change_percentage_24h":0.00351,"market_cap_change_24h":-267295090.28836823,"market_cap_change_percentage_24h":-0.44366,"circulating_supply":59985351054.27856,"total_supply":60039742340.69896,"max_supply":null,"ath":1.17,"ath_change_percentage":-14.73362,"ath_date":"2019-05-08T00:40:28.300Z","atl":0.877647,"atl_change_percentage":13.93242,"atl_date":"2023-03-11T08:02:13.981Z","roi":null,"last_updated":"2025-04-09T16:07:29.767Z"},{"id":"solana","symbol":"sol","name":"Solana","image":"https://coin-images.coingecko.com/coins/images/4128/large/solana.png?1718769756","current_price":106.53,"market_cap":54917716100,"market_cap_rank":7,"fully_diluted_valuation":63709480050,"total_volume":6360105724,"high_24h":107.51,"low_24h":101.86,"price_change_24h":-0.3972401214199124,"price_change_percentage_24h":-0.37149,"market_cap_change_24h":-312579313.39092255,"market_cap_change_percentage_24h":-0.56596,"circulating_supply":515592489.4745838,"total_supply":598133566.9924204,"max_supply":null,"ath":293.31,"ath_change_percentage":-63.71426,"ath_date":"2025-01-19T11:15:27.957Z","atl":0.500801,"atl_change_percentage":21152.03134,"atl_date":"2020-05-11T19:35:23.449Z","roi":null,"last_updated":"2025-04-09T16:07:34.099Z"},{"id":"tron","symbol":"trx","name":"TRON","image":"https://coin-images.coingecko.com/coins/images/1094/large/tron-logo.png?1696502193","current_price":0.230252,"market_cap":21857391367,"market_cap_rank":8,"fully_diluted_valuation":21857401179,"total_volume":927199314,"high_24h":0.234565,"low_24h":0.226703,"price_change_24h":-0.004311002082533155,"price_change_percentage_24h":-1.83789,"market_cap_change_24h":-440080240.6437683,"market_cap_change_percentage_24h":-1.97368,"circulating_supply":94968920867.54453,"total_supply":94968963502.601,"max_supply":null,"ath":0.431288,"ath_change_percentage":-46.64831,"ath_date":"2024-12-04T00:10:40.323Z","atl":0.00180434,"atl_change_percentage":12652.55351,"atl_date":"2017-11-12T00:00:00.000Z","roi":{"times":120.18511040811579,"currency":"usd","percentage":12018.51104081158},"last_updated":"2025-04-09T16:07:30.019Z"},{"id":"dogecoin","symbol":"doge","name":"Dogecoin","image":"https://coin-images.coingecko.com/coins/images/5/large/dogecoin.png?1696501409","current_price":0.146437,"market_cap":21742061293,"market_cap_rank":9,"fully_diluted_valuation":21742223502,"total_volume":1925720120,"high_24h":0.15077,"low_24h":0.137631,"price_change_24h":-0.004333376252632387,"price_change_percentage_24h":-2.87416,"market_cap_change_24h":-699713594.69664,"market_cap_change_percentage_24h":-3.11791,"circulating_supply":148781656383.7051,"total_supply":148782766383.7052,"max_supply":null,"ath":0.731578,"ath_change_percentage":-80.01454,"ath_date":"2021-05-08T05:08:23.458Z","atl":8.69e-05,"atl_change_percentage":168142.74737,"atl_date":"2015-05-06T00:00:00.000Z","roi":null,"last_updated":"2025-04-09T16:07:28.336Z"},{"id":"cardano","symbol":"ada","name":"Cardano","image":"https://coin-images.coingecko.com/coins/images/975/large/cardano.png?1696502090","current_price":0.570525,"market_cap":20505868980,"market_cap_rank":10,"fully_diluted_valuation":25629724358,"total_volume":1259842340,"high_24h":0.591712,"low_24h":0.540605,"price_change_24h":-0.021186938754469753,"price_change_percentage_24h":-3.58062,"market_cap_change_24h":-812780492.727066,"market_cap_change_percentage_24h":-3.81253,"circulating_supply":36003668678.58559,"total_supply":45000000000.0,"max_supply":45000000000.0,"ath":3.09,"ath_change_percentage":-81.54074,"ath_date":"2021-09-02T06:00:10.474Z","atl":0.01925275,"atl_change_percentage":2859.68609,"atl_date":"2020-03-13T02:22:55.044Z","roi":null,"last_updated":"2025-04-09T16:07:24.527Z"},{"id":"staked-ether","symbol":"steth","name":"Lido Staked Ether","image":"https://coin-images.coingecko.com/coins/images/13442/large/steth_logo.png?1696513206","current_price":1487.83,"market_cap":13925284772,"market_cap_rank":11,"fully_diluted_valuation":13925284772,"total_volume":54778730,"high_24h":1526.94,"low_24h":1404.02,"price_change_24h":-39.10441308874533,"price_change_percentage_24h":-2.56097,"market_cap_change_24h":-375275131.2049179,"market_cap_change_percentage_24h":-2.6242,"circulating_supply":9364014.978626767,"total_supply":9364014.978626767,"max_supply":null,"ath":4829.57,"ath_change_percentage":-69.21797,"ath_date":"2021-11-10T14:40:47.256Z","atl":482.9,"atl_change_percentage":207.85905,"atl_date":"2020-12-22T04:08:21.854Z","roi":null,"last_updated":"2025-04-09T16:07:33.641Z"},{"id":"wrapped-bitcoin","symbol":"wbtc","name":"Wrapped Bitcoin","image":"https://coin-images.coingecko.com/coins/images/7598/large/wrapped_bitcoin_wbtc.png?1696507857","current_price":77180,"market_cap":9927486622,"market_cap_rank":12,"fully_diluted_valuation":9927486622,"total_volume":490957376,"high_24h":78270,"low_24h":74489,"price_change_24h":-1090.1876279169373,"price_change_percentage_24h":-1.39285,"market_cap_change_24h":-170100649.517313,"market_cap_change_percentage_24h":-1.68457,"circulating_supply":128915.05657878,"total_supply":128915.05657878,"max_supply":128915.05657878,"ath":108368,"ath_change_percentage":-28.84798,"ath_date":"2025-01-20T07:16:27.137Z","atl":3139.17,"atl_change_percentage":2356.24943,"atl_date":"2019-04-02T00:00:00.000Z","roi":null,"last_updated":"2025-04-09T16:07:31.177Z"},{"id":"leo-token","symbol":"leo","name":"LEO Token","image":"https://coin-images.coingecko.com/coins/images/8418/large/leo-token.png?1696508607","current_price":9.16,"market_cap":8462313654,"market_cap_rank":13,"fully_diluted_valuation":9025663627,"total_volume":4852540,"high_24h":9.22,"low_24h":8.95,"price_change_24h":0.165412,"price_change_percentage_24h":1.83946,"market_cap_change_24h":156936918,"market_cap_change_percentage_24h":1.88958,"circulating_supply":923744341.9,"total_supply":985239504.0,"max_supply":null,"ath":10.14,"ath_change_percentage":-9.62065,"ath_date":"2025-03-10T09:26:43.294Z","atl":0.799859,"atl_change_percentage":1045.20732,"atl_date":"2019-12-24T15:14:35.376Z","roi":null,"last_updated":"2025-04-09T16:07:27.919Z"},{"id":"usds","symbol":"usds","name":"USDS","image":"https://coin-images.coingecko.com/coins/images/39926/large/usds.webp?1726666683","current_price":0.999749,"market_cap":7724554588,"market_cap_rank":14,"fully_diluted_valuation":7720394155,"total_volume":15847931,"high_24h":1.0,"low_24h":0.999221,"price_change_24h":-2.3493640467054e-05,"price_change_percentage_24h":-0.00235,"market_cap_change_24h":-109626537.23165035,"market_cap_change_percentage_24h":-1.39934,"circulating_supply":7726490843.669651,"total_supply":7722329368.559379,"max_supply":null,"ath":1.057,"ath_change_percentage":-5.44296,"ath_date":"2024-10-29T05:40:51.197Z","atl":0.948265,"atl_change_percentage":5.43176,"atl_date":"2024-10-03T13:19:28.826Z","roi":null,"last_updated":"2025-04-09T16:07:29.176Z"},{"id":"the-open-network","symbol":"ton","name":"Toncoin","image":"https://coin-images.coingecko.com/coins/images/17980/large/photo_2024-09-10_17.09.00.jpeg?1725963446","current_price":3.02,"market_cap":7465550246,"market_cap_rank":15,"fully_diluted_valuation":15455115928,"total_volume":198198594,"high_24h":3.07,"low_24h":2.9,"price_change_24h":-0.03925880449258523,"price_change_percentage_24h":-1.28447,"market_cap_change_24h":-96419875.55519009,"market_cap_change_percentage_24h":-1.27506,"circulating_supply":2476485258.024502,"total_supply":5126797397.166953,"max_supply":null,"ath":8.25,"ath_change_percentage":-63.49146,"ath_date":"2024-06-15T00:36:51.509Z","atl":0.519364,"atl_change_percentage":480.18513,"atl_date":"2021-09-21T00:33:11.092Z","roi":null,"last_updated":"2025-04-09T16:07:27.144Z"},{"id":"chainlink","symbol":"link","name":"Chainlink","image":"https://coin-images.coingecko.com/coins/images/877/large/chainlink-new-logo.png?1696502009","current_price":11.37,"market_cap":7248686139,"market_cap_rank":16,"fully_diluted_valuation":11359796996,"total_volume":709120261,"high_24h":11.46,"low_24h":10.51,"price_change_24h":-0.04087773937865791,"price_change_percentage_24h":-0.35822,"market_cap_change_24h":-39022224.07826042,"market_cap_change_percentage_24h":-0.53545,"circulating_supply":638099971.4505637,"total_supply":1000000000.0,"max_supply":1000000000.0,"ath":52.7,"ath_change_percentage":-78.43083,"ath_date":"2021-05-10T00:13:57.214Z","atl":0.148183,"atl_change_percentage":7570.38486,"atl_date":"2017-11-29T00:00:00.000Z","roi":null,"last_updated":"2025-04-09T16:07:35.251Z"},{"id":"avalanche-2","symbol":"avax","name":"Avalanche","image":"https://coin-images.coingecko.com/coins/images/12559/large/Avalanche_Circle_RedWhite_Trans.png?1696512369","current_price":16.8,"market_cap":6979024137,"market_cap_rank":17,"fully_diluted_valuation":7594654599,"total_volume":471729740,"high_24h":17.14,"low_24h":15.67,"price_change_24h":-0.3367079139143847,"price_change_percentage_24h":-1.96443,"market_cap_change_24h":-141598176.1438942,"market_cap_change_percentage_24h":-1.98856,"circulating_supply":415699477.3565326,"total_supply":452368968.1804588,"max_supply":720000000.0,"ath":144.96,"ath_change_percentage":-88.41529,"ath_date":"2021-11-21T14:18:56.538Z","atl":2.8,"atl_change_percentage":499.53408,"atl_date":"2020-12-31T13:15:21.540Z","roi":null,"last_updated":"2025-04-09T16:07:34.623Z"},{"id":"stellar","symbol":"xlm","name":"Stellar","image":"https://coin-images.coingecko.com/coins/images/100/large/fmpFRHHQ_400x400.jpg?1735231350","current_price":0.220585,"market_cap":6779563553,"market_cap_rank":18,"fully_diluted_valuation":11012471657,"total_volume":244734618,"high_24h":0.231922,"low_24h":0.214499,"price_change_24h":-0.011336468117876114,"price_change_percentage_24h":-4.88805,"market_cap_change_24h":-372637922.66220284,"market_cap_change_percentage_24h":-5.21012,"circulating_supply":30782398590.99667,"total_supply":50001786892.81792,"max_supply":50001786892.81792,"ath":0.875563,"ath_change_percentage":-74.81582,"ath_date":"2018-01-03T00:00:00.000Z","atl":0.00047612,"atl_change_percentage":46212.23639,"atl_date":"2015-03-05T00:00:00.000Z","roi":null,"last_updated":"2025-04-09T16:07:35.339Z"},{"id":"shiba-inu","symbol":"shib","name":"Shiba Inu","image":"https://coin-images.coingecko.com/coins/images/11939/large/shiba.png?1696511800","current_price":1.104e-05,"market_cap":6500735205,"market_cap_rank":19,"fully_diluted_valuation":6503537823,"total_volume":270247875,"high_24h":1.114e-05,"low_24h":1.038e-05,"price_change_24h":-1.03480730152e-07,"price_change_percentage_24h":-0.92861,"market_cap_change_24h":-72851905.27871227,"market_cap_change_percentage_24h":-1.10825,"circulating_supply":589250579150602.0,"total_supply":589504618692393.4,"max_supply":null,"ath":8.616e-05,"ath_change_percentage":-87.20126,"ath_date":"2021-10-28T03:54:55.568Z","atl":5.6366e-11,"atl_change_percentage":19563403.86711,"atl_date":"2020-11-28T11:26:25.838Z","roi":null,"last_updated":"2025-04-09T16:07:34.124Z"},{"id":"wrapped-steth","symbol":"wsteth","name":"Wrapped stETH","image":"https://coin-images.coingecko.com/coins/images/18834/large/wstETH.png?1696518295","current_price":1783.22,"market_cap":6371509195,"market_cap_rank":20,"fully_diluted_valuation":6371509195,"total_volume":44595498,"high_24h":1836.72,"low_24h":1673.64,"price_change_24h":-52.78901474343911,"price_change_percentage_24h":-2.87521,"market_cap_change_24h":-199491996.04187012,"market_cap_change_percentage_24h":-3.03595,"circulating_supply":3573063.990039015,"total_supply":3573525.735604511,"max_supply":null,"ath":7256.02,"ath_change_percentage":-75.41952,"ath_date":"2022-05-13T15:09:54.509Z","atl":558.54,"atl_change_percentage":219.32612,"atl_date":"2022-05-13T01:36:45.053Z","roi":null,"last_updated":"2025-04-09T16:07:31.450Z"},{"id":"sui","symbol":"sui","name":"Sui","image":"https://coin-images.coingecko.com/coins/images/26375/large/sui-ocean-square.png?1727791290","current_price":1.96,"market_cap":6359787380,"market_cap_rank":21,"fully_diluted_valuation":19568679512,"total_volume":1419082867,"high_24h":2.01,"low_24h":1.87,"price_change_24h":-0.053366348709445566,"price_change_percentage_24h":-2.65459,"market_cap_change_24h":-173786453.65934086,"market_cap_change_percentage_24h":-2.6599,"circulating_supply":3249982900.458887,"total_supply":10000000000.0,"max_supply":10000000000.0,"ath":5.35,"ath_change_percentage":-63.47355,"ath_date":"2025-01-04T22:56:18.063Z","atl":0.364846,"atl_change_percentage":435.26953,"atl_date":"2023-10-19T10:40:30.078Z","roi":null,"last_updated":"2025-04-09T16:07:26.174Z"},{"id":"hedera-hashgraph","symbol":"hbar","name":"Hedera","image":"https://coin-images.coingecko.com/coins/images/3688/large/hbar.png?1696504364","current_price":0.150476,"market_cap":6328028403,"market_cap_rank":22,"fully_diluted_valuation":7492576923,"total_volume":491652393,"high_24h":0.158681,"low_24h":0.142798,"price_change_24h":-0.008205464253578654,"price_change_percentage_24h":-5.17103,"market_cap_change_24h":-381697056.8531389,"market_cap_change_percentage_24h":-5.68871,"circulating_supply":42228651556.64356,"total_supply":50000000000.0,"max_supply":50000000000.0,"ath":0.569229,"ath_change_percentage":-73.75285,"ath_date":"2021-09-15T10:40:28.318Z","atl":0.00986111,"atl_change_percentage":1415.10725,"atl_date":"2020-01-02T17:30:24.852Z","roi":null,"last_updated":"2025-04-09T16:07:27.597Z"},{"id":"mantra-dao","symbol":"om","name":"MANTRA","image":"https://coin-images.coingecko.com/coins/images/12151/large/OM_Token.png?1696511991","current_price":6.32,"market_cap":6105245699,"market_cap_rank":23,"fully_diluted_valuation":11470925394,"total_volume":124653757,"high_24h":6.32,"low_24h":6.11,"price_change_24h":0.123833,"price_change_percentage_24h":1.99721,"market_cap_change_24h":110610545,"market_cap_change_percentage_24h":1.84516,"circulating_supply":966261227.49,"total_supply":1815473282.69,"max_supply":null,"ath":8.99,"ath_change_percentage":-29.64239,"ath_date":"2025-02-23T01:52:21.073Z","atl":0.01726188,"atl_change_percentage":36523.40626,"atl_date":"2023-10-12T17:25:09.068Z","roi":null,"last_updated":"2025-04-09T16:07:29.126Z"},{"id":"bitcoin-cash","symbol":"bch","name":"Bitcoin Cash","image":"https://coin-images.coingecko.com/coins/images/780/large/bitcoin-cash-circle.png?1696501932","current_price":273.79,"market_cap":5434623738,"market_cap_rank":24,"fully_diluted_valuation":5434628015,"total_volume":205682484,"high_24h":280.4,"low_24h":260.29,"price_change_24h":-6.563298908458535,"price_change_percentage_24h":-2.34106,"market_cap_change_24h":-120601498.04739666,"market_cap_change_percentage_24h":-2.17096,"circulating_supply":19853671.77165078,"total_supply":19853687.39665078,"max_supply":21000000.0,"ath":3785.82,"ath_change_percentage":-92.7678,"ath_date":"2017-12-20T00:00:00.000Z","atl":76.93,"atl_change_percentage":255.88335,"atl_date":"2018-12-16T00:00:00.000Z","roi":null,"last_updated":"2025-04-09T16:07:34.568Z"},{"id":"litecoin","symbol":"ltc","name":"Litecoin","image":"https://coin-images.coingecko.com/coins/images/2/large/litecoin.png?1696501400","current_price":71.42,"market_cap":5406005371,"market_cap_rank":25,"fully_diluted_valuation":5406008048,"total_volume":573792841,"high_24h":71.79,"low_24h":66.79,"price_change_24h":0.098616,"price_change_percentage_24h":0.13827,"market_cap_change_24h":-8050176.009994507,"market_cap_change_percentage_24h":-0.14869,"circulating_supply":75727376.98347135,"total_supply":75727520.73347135,"max_supply":84000000.0,"ath":410.26,"ath_change_percentage":-82.59012,"ath_date":"2021-05-10T03:13:07.904Z","atl":1.15,"atl_change_percentage":6117.19391,"atl_date":"2015-01-14T00:00:00.000Z","roi":null,"last_updated":"2025-04-09T16:07:29.703Z"},{"id":"binance-bridged-usdt-bnb-smart-chain","symbol":"bsc-usd","name":"Binance Bridged USDT (BNB Smart Chain)","image":"https://coin-images.coingecko.com/coins/images/35021/large/USDT.png?1707233575","current_price":0.998898,"market_cap":5181722829,"market_cap_rank":26,"fully_diluted_valuation":5181722829,"total_volume":305005709,"high_24h":1.007,"low_24h":0.989306,"price_change_24h":5.038e-05,"price_change_percentage_24h":0.00504,"market_cap_change_24h":-2815926.7572774887,"market_cap_change_percentage_24h":-0.05431,"circulating_supply":5184994300.618545,"total_supply":5184994300.618545,"max_supply":null,"ath":1.05,"ath_change_percentage":-4.83582,"ath_date":"2024-08-05T14:21:42.527Z","atl":0.942186,"atl_change_percentage":6.04986,"atl_date":"2024-12-05T22:30:39.827Z","roi":null,"last_updated":"2025-04-09T16:07:24.815Z"},{"id":"polkadot","symbol":"dot","name":"Polkadot","image":"https://coin-images.coingecko.com/coins/images/12171/large/polkadot.png?1696512008","current_price":3.37,"market_cap":5133431952,"market_cap_rank":27,"fully_diluted_valuation":5133431952,"total_volume":242148969,"high_24h":3.59,"low_24h":3.26,"price_change_24h":-0.21365473554986636,"price_change_percentage_24h":-5.95364,"market_cap_change_24h":-329960570.1642704,"market_cap_change_percentage_24h":-6.03948,"circulating_supply":1522267060.0,"total_supply":1522267060.0,"max_supply":null,"ath":54.98,"ath_change_percentage":-93.87069,"ath_date":"2021-11-04T14:10:09.301Z","atl":2.7,"atl_change_percentage":24.9307,"atl_date":"2020-08-20T05:48:11.359Z","roi":null,"last_updated":"2025-04-09T16:07:32.406Z"},{"id":"ethena-usde","symbol":"usde","name":"Ethena USDe","image":"https://coin-images.coingecko.com/coins/images/33613/large/usde.png?1733810059","current_price":0.998192,"market_cap":5076258927,"market_cap_rank":28,"fully_diluted_valuation":5076258927,"total_volume":91375815,"high_24h":0.999675,"low_24h":0.997496,"price_change_24h":-0.00059642263043802,"price_change_percentage_24h":-0.05971,"market_cap_change_24h":-22074987.98353672,"market_cap_change_percentage_24h":-0.43298,"circulating_supply":5084009049.747064,"total_supply":5084009049.747064,"max_supply":null,"ath":1.032,"ath_change_percentage":-3.27687,"ath_date":"2023-12-20T15:38:34.596Z","atl":0.929486,"atl_change_percentage":7.39936,"atl_date":"2024-10-04T07:57:15.809Z","roi":null,"last_updated":"2025-04-09T16:07:28.733Z"},{"id":"bitget-token","symbol":"bgb","name":"Bitget Token","image":"https://coin-images.coingecko.com/coins/images/11610/large/Bitget_logo.png?1736925727","current_price":4.05,"market_cap":4864307313,"market_cap_rank":29,"fully_diluted_valuation":4864307313,"total_volume":286437110,"high_24h":4.14,"low_24h":3.88,"price_change_24h":-0.034628903838537894,"price_change_percentage_24h":-0.84681,"market_cap_change_24h":-41624114.57217789,"market_cap_change_percentage_24h":-0.84844,"circulating_supply":1199999994.2,"total_supply":1199999994.2,"max_supply":2000000000.0,"ath":8.45,"ath_change_percentage":-52.06244,"ath_date":"2024-12-27T11:41:24.992Z","atl":0.0142795,"atl_change_percentage":28268.49193,"atl_date":"2020-06-25T04:17:05.895Z","roi":null,"last_updated":"2025-04-09T16:07:33.884Z"},{"id":"hyperliquid","symbol":"hype","name":"Hyperliquid","image":"https://coin-images.coingecko.com/coins/images/50882/large/hyperliquid.jpg?1729431300","current_price":12.9,"market_cap":4315709852,"market_cap_rank":30,"fully_diluted_valuation":12923941856,"total_volume":224130552,"high_24h":12.99,"low_24h":10.81,"price_change_24h":1.39,"price_change_percentage_24h":12.04457,"market_cap_change_24h":452973078,"market_cap_change_percentage_24h":11.72674,"circulating_supply":333928180.0,"total_supply":999990391.0,"max_supply":1000000000.0,"ath":34.96,"ath_change_percentage":-63.12447,"ath_date":"2024-12-22T03:56:00.276Z","atl":3.81,"atl_change_percentage":238.46977,"atl_date":"2024-11-29T09:30:30.871Z","roi":null,"last_updated":"2025-04-09T16:07:27.579Z"},{"id":"weth","symbol":"weth","name":"WETH","image":"https://coin-images.coingecko.com/coins/images/2518/large/weth.png?1696503332","current_price":1488.16,"market_cap":4101213838,"market_cap_rank":31,"fully_diluted_valuation":4101213838,"total_volume":336521315,"high_24h":1530.66,"low_24h":1395.54,"price_change_24h":-41.18367258429362,"price_change_percentage_24h":-2.6929,"market_cap_change_24h":-91646191.28737402,"market_cap_change_percentage_24h":-2.18577,"circulating_supply":2755742.604653217,"total_supply":2755742.604653217,"max_supply":null,"ath":4799.89,"ath_change_percentage":-68.99017,"ath_date":"2021-11-09T00:00:00.000Z","atl":82.1,"atl_change_percentage":1712.88318,"atl_date":"2018-12-15T00:00:00.000Z","roi":null,"last_updated":"2025-04-09T16:07:31.379Z"},{"id":"whitebit","symbol":"wbt","name":"WhiteBIT Coin","image":"https://coin-images.coingecko.com/coins/images/27045/large/wbt_token.png?1696526096","current_price":27.78,"market_cap":4003155047,"market_cap_rank":32,"fully_diluted_valuation":9099967383,"total_volume":56351853,"high_24h":27.94,"low_24h":27.36,"price_change_24h":-0.03258413861932041,"price_change_percentage_24h":-0.11717,"market_cap_change_24h":-4797413.219686985,"market_cap_change_percentage_24h":-0.1197,"circulating_supply":144118517.10815412,"total_supply":327610045.0,"max_supply":400000000.0,"ath":31.28,"ath_change_percentage":-11.18617,"ath_date":"2025-03-02T22:22:36.852Z","atl":3.06,"atl_change_percentage":807.24032,"atl_date":"2023-02-13T19:01:21.899Z","roi":null,"last_updated":"2025-04-09T16:07:29.507Z"},{"id":"pi-network","symbol":"pi","name":"Pi Network","image":"https://coin-images.coingecko.com/coins/images/54342/large/pi_network.jpg?1739347576","current_price":0.575101,"market_cap":3934749655,"market_cap_rank":33,"fully_diluted_valuation":6053461007,"total_volume":199158046,"high_24h":0.580702,"low_24h":0.549405,"price_change_24h":-0.003631684547834135,"price_change_percentage_24h":-0.62752,"market_cap_change_24h":-19204256.466837883,"market_cap_change_percentage_24h":-0.4857,"circulating_supply":6844664655.274765,"total_supply":10530253315.80733,"max_supply":100000000000.0,"ath":2.99,"ath_change_percentage":-80.74088,"ath_date":"2025-02-26T16:41:03.732Z","atl":0.406999,"atl_change_percentage":41.37329,"atl_date":"2025-04-05T04:50:37.033Z","roi":null,"last_updated":"2025-04-09T16:07:32.333Z"},{"id":"monero","symbol":"xmr","name":"Monero","image":"https://coin-images.coingecko.com/coins/images/69/large/monero_logo.png?1696501460","current_price":195.09,"market_cap":3593153517,"market_cap_rank":34,"fully_diluted_valuation":3593153517,"total_volume":76011895,"high_24h":202.92,"low_24h":192.6,"price_change_24h":-7.8320800091851766,"price_change_percentage_24h":-3.85968,"market_cap_change_24h":-146067956.98432684,"market_cap_change_percentage_24h":-3.90637,"circulating_supply":18446744.07370955,"total_supply":18446744.07370955,"max_supply":null,"ath":542.33,"ath_change_percentage":-64.08249,"ath_date":"2018-01-09T00:00:00.000Z","atl":0.216177,"atl_change_percentage":90006.77666,"atl_date":"2015-01-14T00:00:00.000Z","roi":null,"last_updated":"2025-04-09T16:07:31.860Z"},{"id":"wrapped-eeth","symbol":"weeth","name":"Wrapped eETH","image":"https://coin-images.coingecko.com/coins/images/33033/large/weETH.png?1701438396","current_price":1582.44,"market_cap":3345383449,"market_cap_rank":35,"fully_diluted_valuation":3345383449,"total_volume":8751618,"high_24h":1627.11,"low_24h":1505.24,"price_change_24h":-44.66500999232653,"price_change_percentage_24h":-2.74506,"market_cap_change_24h":-107071229.23573256,"market_cap_change_percentage_24h":-3.10131,"circulating_supply":2114384.266465718,"total_supply":2114384.458705609,"max_supply":null,"ath":4311.81,"ath_change_percentage":-63.30539,"ath_date":"2024-12-06T20:32:25.758Z","atl":1505.24,"atl_change_percentage":5.11329,"atl_date":"2025-04-09T03:45:31.391Z","roi":null,"last_updated":"2025-04-09T16:07:31.225Z"},{"id":"dai","symbol":"dai","name":"Dai","image":"https://coin-images.coingecko.com/coins/images/9956/large/Badge_Dai.png?1696509996","current_price":0.999815,"market_cap":3175740337,"market_cap_rank":36,"fully_diluted_valuation":3178130812,"total_volume":149857653,"high_24h":1.0,"low_24h":0.99945,"price_change_24h":-0.000330830046651243,"price_change_percentage_24h":-0.03308,"market_cap_change_24h":3812840,"market_cap_change_percentage_24h":0.12021,"circulating_supply":3176426010.416632,"total_supply":3178817000.981886,"max_supply":null,"ath":1.22,"ath_change_percentage":-17.97554,"ath_date":"2020-03-13T03:02:50.373Z","atl":0.88196,"atl_change_percentage":13.36356,"atl_date":"2023-03-11T07:50:50.514Z","roi":null,"last_updated":"2025-04-09T16:07:26.449Z"},{"id":"okb","symbol":"okb","name":"OKB","image":"https://coin-images.coingecko.com/coins/images/4463/large/WeChat_Image_20220118095654.png?1696505053","current_price":52.0,"market_cap":3121038950,"market_cap_rank":37,"fully_diluted_valuation":12273885439,"total_volume":25836738,"high_24h":52.61,"low_24h":48.9,"price_change_24h":-0.6162053755311234,"price_change_percentage_24h":-1.17122,"market_cap_change_24h":-37964880.59902954,"market_cap_change_percentage_24h":-1.2018,"circulating_supply":60000000.0,"total_supply":235957685.3,"max_supply":300000000.0,"ath":73.8,"ath_change_percentage":-29.42412,"ath_date":"2024-03-14T00:30:12.502Z","atl":0.580608,"atl_change_percentage":8871.17566,"atl_date":"2019-01-14T00:00:00.000Z","roi":null,"last_updated":"2025-04-09T16:07:30.896Z"},{"id":"susds","symbol":"susds","name":"sUSDS","image":"https://coin-images.coingecko.com/coins/images/52721/large/sUSDS_Coin.png?1734086971","current_price":1.047,"market_cap":3046628563,"market_cap_rank":38,"fully_diluted_valuation":3044317794,"total_volume":4330286,"high_24h":1.048,"low_24h":1.045,"price_change_24h":0.00093699,"price_change_percentage_24h":0.08959,"market_cap_change_24h":13887157,"market_cap_change_percentage_24h":0.45791,"circulating_supply":2909413095.680336,"total_supply":2907206399.982083,"max_supply":null,"ath":1.088,"ath_change_percentage":-3.77477,"ath_date":"2025-02-03T02:31:35.208Z","atl":0.961716,"atl_change_percentage":8.8521,"atl_date":"2025-01-04T01:21:08.460Z","roi":null,"last_updated":"2025-04-09T16:07:35.821Z"},{"id":"uniswap","symbol":"uni","name":"Uniswap","image":"https://coin-images.coingecko.com/coins/images/12504/large/uniswap-logo.png?1720676669","current_price":4.87,"market_cap":2921039506,"market_cap_rank":39,"fully_diluted_valuation":4864482671,"total_volume":214632788,"high_24h":5.1,"low_24h":4.59,"price_change_24h":-0.2283726247982214,"price_change_percentage_24h":-4.48078,"market_cap_change_24h":-141667318.88095236,"market_cap_change_percentage_24h":-4.62556,"circulating_supply":600483073.71,"total_supply":1000000000.0,"max_supply":1000000000.0,"ath":44.92,"ath_change_percentage":-89.17316,"ath_date":"2021-05-03T05:25:04.822Z","atl":1.03,"atl_change_percentage":372.07761,"atl_date":"2020-09-17T01:20:38.214Z","roi":null,"last_updated":"2025-04-09T16:07:30.095Z"},{"id":"pepe","symbol":"pepe","name":"Pepe","image":"https://coin-images.coingecko.com/coins/images/29850/large/pepe-token.jpeg?1696528776","current_price":6.4e-06,"market_cap":2687253061,"market_cap_rank":40,"fully_diluted_valuation":2687253061,"total_volume":964412916,"high_24h":6.41e-06,"low_24h":5.85e-06,"price_change_24h":2.05719e-07,"price_change_percentage_24h":3.32316,"market_cap_change_24h":85600520,"market_cap_change_percentage_24h":3.29024,"circulating_supply":420690000000000.0,"total_supply":420690000000000.0,"max_supply":420690000000000.0,"ath":2.803e-05,"ath_change_percentage":-77.19569,"ath_date":"2024-12-09T16:30:35.828Z","atl":5.5142e-08,"atl_change_percentage":11491.14408,"atl_date":"2023-04-18T02:14:41.591Z","roi":null,"last_updated":"2025-04-09T16:07:32.930Z"},{"id":"coinbase-wrapped-btc","symbol":"cbbtc","name":"Coinbase Wrapped BTC","image":"https://coin-images.coingecko.com/coins/images/40143/large/cbbtc.webp?1726136727","current_price":77274,"market_cap":2670056534,"market_cap_rank":41,"fully_diluted_valuation":2670056534,"total_volume":452128429,"high_24h":78338,"low_24h":74503,"price_change_24h":-1063.3698263295373,"price_change_percentage_24h":-1.35742,"market_cap_change_24h":80011121,"market_cap_change_percentage_24h":3.08918,"circulating_supply":34553.01274693,"total_supply":34553.01274693,"max_supply":null,"ath":108953,"ath_change_percentage":-29.09414,"ath_date":"2025-01-20T09:20:53.854Z","atl":57439,"atl_change_percentage":34.49792,"atl_date":"2024-09-12T14:07:41.775Z","roi":null,"last_updated":"2025-04-09T16:07:35.118Z"},{"id":"aptos","symbol":"apt","name":"Aptos","image":"https://coin-images.coingecko.com/coins/images/26455/large/aptos_round.png?1696525528","current_price":4.36,"market_cap":2635949913,"market_cap_rank":42,"fully_diluted_valuation":4996949514,"total_volume":182033389,"high_24h":4.56,"low_24h":4.19,"price_change_24h":-0.19832600723131488,"price_change_percentage_24h":-4.3538,"market_cap_change_24h":-119995991.78614044,"market_cap_change_percentage_24h":-4.35408,"circulating_supply":605137268.023286,"total_supply":1147153958.88662,"max_supply":null,"ath":19.92,"ath_change_percentage":-78.13484,"ath_date":"2023-01-26T14:25:17.390Z","atl":3.08,"atl_change_percentage":41.42584,"atl_date":"2022-12-29T21:35:14.796Z","roi":null,"last_updated":"2025-04-09T16:07:34.811Z"},{"id":"gatechain-token","symbol":"gt","name":"Gate","image":"https://coin-images.coingecko.com/coins/images/8183/large/200X200.png?1735246724","current_price":21.04,"market_cap":2584151492,"market_cap_rank":43,"fully_diluted_valuation":6307393543,"total_volume":21112653,"high_24h":21.27,"low_24h":20.05,"price_change_24h":-0.20036360612705906,"price_change_percentage_24h":-0.94318,"market_cap_change_24h":-25600434.00965786,"market_cap_change_percentage_24h":-0.98095,"circulating_supply":122910587.76765741,"total_supply":300000000.0,"max_supply":null,"ath":25.94,"ath_change_percentage":-18.91681,"ath_date":"2025-01-25T03:07:37.823Z","atl":0.25754,"atl_change_percentage":8066.68998,"atl_date":"2020-03-13T02:18:02.481Z","roi":null,"last_updated":"2025-04-09T16:07:26.811Z"},{"id":"ondo-finance","symbol":"ondo","name":"Ondo","image":"https://coin-images.coingecko.com/coins/images/26580/large/ONDO.png?1696525656","current_price":0.745765,"market_cap":2349629929,"market_cap_rank":44,"fully_diluted_valuation":7437638343,"total_volume":213219819,"high_24h":0.75131,"low_24h":0.687115,"price_change_24h":-0.005087654229693483,"price_change_percentage_24h":-0.67758,"market_cap_change_24h":-24271208.937411785,"market_cap_change_percentage_24h":-1.02242,"circulating_supply":3159107529.0,"total_supply":10000000000.0,"max_supply":10000000000.0,"ath":2.14,"ath_change_percentage":-65.28084,"ath_date":"2024-12-16T00:36:00.777Z","atl":0.082171,"atl_change_percentage":804.26605,"atl_date":"2024-01-18T12:14:30.524Z","roi":null,"last_updated":"2025-04-09T16:07:31.373Z"},{"id":"near","symbol":"near","name":"NEAR Protocol","image":"https://coin-images.coingecko.com/coins/images/10365/large/near.jpg?1696510367","current_price":1.9,"market_cap":2283134089,"market_cap_rank":45,"fully_diluted_valuation":2366356728,"total_volume":337680442,"high_24h":2.06,"low_24h":1.83,"price_change_24h":-0.15896828778550431,"price_change_percentage_24h":-7.70347,"market_cap_change_24h":-196014589.7931471,"market_cap_change_percentage_24h":-7.90653,"circulating_supply":1200444348.0,"total_supply":1244296626.0,"max_supply":null,"ath":20.44,"ath_change_percentage":-90.70343,"ath_date":"2022-01-16T22:09:45.873Z","atl":0.526762,"atl_change_percentage":260.70248,"atl_date":"2020-11-04T16:09:15.137Z","roi":null,"last_updated":"2025-04-09T16:07:30.848Z"},{"id":"internet-computer","symbol":"icp","name":"Internet Computer","image":"https://coin-images.coingecko.com/coins/images/14495/large/Internet_Computer_logo.png?1696514180","current_price":4.64,"market_cap":2243124144,"market_cap_rank":47,"fully_diluted_valuation":2470063489,"total_volume":89672565,"high_24h":4.68,"low_24h":4.49,"price_change_24h":-0.024348503458658577,"price_change_percentage_24h":-0.52171,"market_cap_change_24h":-14739077.422323227,"market_cap_change_percentage_24h":-0.65279,"circulating_supply":483102401.7309553,"total_supply":531978404.89691,"max_supply":null,"ath":700.65,"ath_change_percentage":-99.33766,"ath_date":"2021-05-10T16:05:53.653Z","atl":2.87,"atl_change_percentage":61.97632,"atl_date":"2023-09-22T00:29:57.369Z","roi":null,"last_updated":"2025-04-09T16:07:28.135Z"},{"id":"mantle","symbol":"mnt","name":"Mantle","image":"https://coin-images.coingecko.com/coins/images/30980/large/Mantle-Logo-mark.png?1739213200","current_price":0.665562,"market_cap":2243009940,"market_cap_rank":46,"fully_diluted_valuation":4145990037,"total_volume":337069667,"high_24h":0.686308,"low_24h":0.649305,"price_change_24h":-0.020746388251449033,"price_change_percentage_24h":-3.0229,"market_cap_change_24h":-68551885.65292215,"market_cap_change_percentage_24h":-2.96561,"circulating_supply":3364694382.83684,"total_supply":6219316794.99,"max_supply":6219316794.99,"ath":1.54,"ath_change_percentage":-56.69536,"ath_date":"2024-04-08T09:45:25.482Z","atl":0.307978,"atl_change_percentage":116.35809,"atl_date":"2023-10-18T02:50:46.942Z","roi":null,"last_updated":"2025-04-09T16:07:28.716Z"},{"id":"crypto-com-chain","symbol":"cro","name":"Cronos","image":"https://coin-images.coingecko.com/coins/images/7310/large/cro_token_logo.png?1696507599","current_price":0.08162,"market_cap":2236882402,"market_cap_rank":48,"fully_diluted_valuation":7942034737,"total_volume":33025542,"high_24h":0.083247,"low_24h":0.077373,"price_change_24h":-0.001625286004350218,"price_change_percentage_24h":-1.9524,"market_cap_change_24h":-47988505.41173887,"market_cap_change_percentage_24h":-2.10027,"circulating_supply":27445676982.03125,"total_supply":97445733422.36987,"max_supply":null,"ath":0.965407,"ath_change_percentage":-91.56659,"ath_date":"2021-11-24T15:53:54.855Z","atl":0.0121196,"atl_change_percentage":571.77759,"atl_date":"2019-02-08T00:00:00.000Z","roi":null,"last_updated":"2025-04-09T16:07:35.292Z"},{"id":"tokenize-xchange","symbol":"tkx","name":"Tokenize Xchange","image":"https://coin-images.coingecko.com/coins/images/4984/large/TKX_-_Logo_-_RGB-15.png?1696505519","current_price":27.98,"market_cap":2231250532,"market_cap_rank":49,"fully_diluted_valuation":2789202658,"total_volume":9377795,"high_24h":29.92,"low_24h":27.76,"price_change_24h":-1.9001385537756654,"price_change_percentage_24h":-6.36016,"market_cap_change_24h":-159271286.94246292,"market_cap_change_percentage_24h":-6.66262,"circulating_supply":79995999.05112354,"total_supply":100000000.0,"max_supply":100000000.0,"ath":50.43,"ath_change_percentage":-44.69354,"ath_date":"2025-01-03T19:12:43.038Z","atl":0.111255,"atl_change_percentage":24970.21201,"atl_date":"2019-04-28T00:00:00.000Z","roi":{"times":95.30117541541198,"currency":"usd","percentage":9530.117541541198},"last_updated":"2025-04-09T16:07:28.550Z"},{"id":"ethena-staked-usde","symbol":"susde","name":"Ethena Staked USDe","image":"https://coin-images.coingecko.com/coins/images/33669/large/sUSDe-Symbol-Color.png?1716307680","current_price":1.16,"market_cap":2157020745,"market_cap_rank":50,"fully_diluted_valuation":2156921420,"total_volume":17931278,"high_24h":1.17,"low_24h":1.16,"price_change_24h":-0.001965750753365691,"price_change_percentage_24h":-0.16875,"market_cap_change_24h":-36191098.39831734,"market_cap_change_percentage_24h":-1.65014,"circulating_supply":1854629241.330618,"total_supply":1854543840.332502,"max_supply":null,"ath":1.29,"ath_change_percentage":-9.90343,"ath_date":"2025-01-29T17:52:32.991Z","atl":1.012,"atl_change_percentage":14.89758,"atl_date":"2024-04-03T14:23:03.162Z","roi":null,"last_updated":"2025-04-09T16:07:27.144Z"},{"id":"ethereum-classic","symbol":"etc","name":"Ethereum Classic","image":"https://coin-images.coingecko.com/coins/images/453/large/ethereum-classic-logo.png?1696501717","current_price":14.22,"market_cap":2152768700,"market_cap_rank":51,"fully_diluted_valuation":2152768700,"total_volume":103186866,"high_24h":14.36,"low_24h":13.66,"price_change_24h":-0.13749957129814128,"price_change_percentage_24h":-0.95782,"market_cap_change_24h":-21936396.09879875,"market_cap_change_percentage_24h":-1.00871,"circulating_supply":151454738.5686912,"total_supply":151455276.6166912,"max_supply":210700000.0,"ath":167.09,"ath_change_percentage":-91.49065,"ath_date":"2021-05-06T18:34:22.133Z","atl":0.615038,"atl_change_percentage":2211.70825,"atl_date":"2016-07-25T00:00:00.000Z","roi":{"times":30.595658211171912,"currency":"usd","percentage":3059.5658211171913},"last_updated":"2025-04-09T16:07:27.051Z"},{"id":"blackrock-usd-institutional-digital-liquidity-fund","symbol":"buidl","name":"BlackRock USD Institutional Digital Liquidity Fund","image":"https://coin-images.coingecko.com/coins/images/36291/large/blackrock.png?1711013223","current_price":1.0,"market_cap":2005184991,"market_cap_rank":52,"fully_diluted_valuation":2005184991,"total_volume":0.0,"high_24h":1.0,"low_24h":1.0,"price_change_24h":0.0,"price_change_percentage_24h":0.0,"market_cap_change_24h":29177158,"market_cap_change_percentage_24h":1.47657,"circulating_supply":2005184990.889999,"total_supply":2005184990.889999,"max_supply":null,"ath":1.0,"ath_change_percentage":0.0,"ath_date":"2025-02-12T05:00:10.912Z","atl":1.0,"atl_change_percentage":0.0,"atl_date":"2025-02-12T05:45:10.196Z","roi":null,"last_updated":"2025-04-09T16:05:07.135Z"},{"id":"aave","symbol":"aave","name":"Aave","image":"https://coin-images.coingecko.com/coins/images/12645/large/aave-token-round.png?1720472354","current_price":128.52,"market_cap":1939112700,"market_cap_rank":53,"fully_diluted_valuation":2054921992,"total_volume":348312335,"high_24h":131.25,"low_24h":120.58,"price_change_24h":-2.73262574960296,"price_change_percentage_24h":-2.08192,"market_cap_change_24h":-42018536.62327051,"market_cap_change_percentage_24h":-2.12094,"circulating_supply":15098287.585144175,"total_supply":16000000.0,"max_supply":16000000.0,"ath":661.69,"ath_change_percentage":-80.60312,"ath_date":"2021-05-18T21:19:59.514Z","atl":26.02,"atl_change_percentage":393.2042,"atl_date":"2020-11-05T09:20:11.928Z","roi":null,"last_updated":"2025-04-09T16:07:33.747Z"},{"id":"cosmos","symbol":"atom","name":"Cosmos Hub","image":"https://coin-images.coingecko.com/coins/images/1481/large/cosmos_hub.png?1696502525","current_price":4.28,"market_cap":1901420691,"market_cap_rank":54,"fully_diluted_valuation":1901433033,"total_volume":162836969,"high_24h":4.31,"low_24h":4.03,"price_change_24h":0.00884884,"price_change_percentage_24h":0.20707,"market_cap_change_24h":4760549,"market_cap_change_percentage_24h":0.251,"circulating_supply":444184536.309919,"total_supply":444187419.443499,"max_supply":null,"ath":44.45,"ath_change_percentage":-90.36808,"ath_date":"2022-01-17T00:34:41.497Z","atl":1.16,"atl_change_percentage":269.05011,"atl_date":"2020-03-13T02:27:44.591Z","roi":{"times":41.82310016513748,"currency":"usd","percentage":4182.310016513748},"last_updated":"2025-04-09T16:07:26.388Z"},{"id":"first-digital-usd","symbol":"fdusd","name":"First Digital USD","image":"https://coin-images.coingecko.com/coins/images/31079/large/FDUSD_icon_black.png?1731097953","current_price":1.0,"market_cap":1885110588,"market_cap_rank":55,"fully_diluted_valuation":1885110588,"total_volume":4025877025,"high_24h":1.01,"low_24h":0.992015,"price_change_24h":0.00090589,"price_change_percentage_24h":0.09067,"market_cap_change_24h":-62580899.40780926,"market_cap_change_percentage_24h":-3.21308,"circulating_supply":1885092709.391388,"total_supply":1885092709.391388,"max_supply":null,"ath":1.15,"ath_change_percentage":-13.14386,"ath_date":"2025-02-03T02:30:49.959Z","atl":0.940377,"atl_change_percentage":6.34063,"atl_date":"2024-12-05T22:30:51.394Z","roi":null,"last_updated":"2025-04-09T16:07:27.724Z"},{"id":"vechain","symbol":"vet","name":"VeChain","image":"https://coin-images.coingecko.com/coins/images/1167/large/VET.png?1742383283","current_price":0.02040611,"market_cap":1753893340,"market_cap_rank":56,"fully_diluted_valuation":1753893340,"total_volume":58980422,"high_24h":0.02055137,"low_24h":0.01904829,"price_change_24h":-0.000133044669830811,"price_change_percentage_24h":-0.64776,"market_cap_change_24h":-10739451.66888547,"market_cap_change_percentage_24h":-0.60859,"circulating_supply":85985041177.0,"total_supply":85985041177.0,"max_supply":86712634466.0,"ath":0.280991,"ath_change_percentage":-92.73588,"ath_date":"2021-04-19T01:08:21.675Z","atl":0.00191713,"atl_change_percentage":964.69043,"atl_date":"2020-03-13T02:29:59.652Z","roi":{"times":3.8038758549247795,"currency":"eth","percentage":380.38758549247797},"last_updated":"2025-04-09T16:07:29.612Z"},{"id":"fasttoken","symbol":"ftn","name":"Fasttoken","image":"https://coin-images.coingecko.com/coins/images/28478/large/lightenicon_200x200.png?1696527472","current_price":4.03,"market_cap":1732290662,"market_cap_rank":57,"fully_diluted_valuation":3506461257,"total_volume":49965290,"high_24h":4.04,"low_24h":4.02,"price_change_24h":-0.001378854489338721,"price_change_percentage_24h":-0.03423,"market_cap_change_24h":-499525.2620110512,"market_cap_change_percentage_24h":-0.02883,"circulating_supply":430171298.6,"total_supply":870742437.0,"max_supply":1000000000.0,"ath":4.12,"ath_change_percentage":-2.35169,"ath_date":"2025-04-07T14:20:34.647Z","atl":0.398142,"atl_change_percentage":911.6216,"atl_date":"2023-01-21T10:15:39.503Z","roi":null,"last_updated":"2025-04-09T16:07:26.191Z"},{"id":"bittensor","symbol":"tao","name":"Bittensor","image":"https://coin-images.coingecko.com/coins/images/28452/large/ARUsPeNQ_400x400.jpeg?1696527447","current_price":201.47,"market_cap":1727574837,"market_cap_rank":58,"fully_diluted_valuation":4230953901,"total_volume":120883965,"high_24h":204.57,"low_24h":191.22,"price_change_24h":-3.098262682816028,"price_change_percentage_24h":-1.51451,"market_cap_change_24h":-23755580.56582117,"market_cap_change_percentage_24h":-1.35643,"circulating_supply":8574679.0,"total_supply":21000000.0,"max_supply":21000000.0,"ath":757.6,"ath_change_percentage":-73.41058,"ath_date":"2024-03-07T18:45:36.466Z","atl":30.83,"atl_change_percentage":553.39908,"atl_date":"2023-05-14T08:57:53.732Z","roi":null,"last_updated":"2025-04-09T16:07:23.203Z"},{"id":"lombard-staked-btc","symbol":"lbtc","name":"Lombard Staked BTC","image":"https://coin-images.coingecko.com/coins/images/39969/large/LBTC_Logo.png?1724959872","current_price":77152,"market_cap":1644348102,"market_cap_rank":59,"fully_diluted_valuation":1644348102,"total_volume":18675119,"high_24h":78242,"low_24h":74539,"price_change_24h":-1090.394180068528,"price_change_percentage_24h":-1.39362,"market_cap_change_24h":-21329160.5750103,"market_cap_change_percentage_24h":-1.28051,"circulating_supply":21313.20278941792,"total_supply":21313.20278941792,"max_supply":null,"ath":114576,"ath_change_percentage":-32.66046,"ath_date":"2025-02-04T01:47:44.052Z","atl":52119,"atl_change_percentage":48.03469,"atl_date":"2024-09-06T21:01:52.094Z","roi":null,"last_updated":"2025-04-09T16:07:28.504Z"},{"id":"kaspa","symbol":"kas","name":"Kaspa","image":"https://coin-images.coingecko.com/coins/images/25751/large/kaspa-icon-exchanges.png?1696524837","current_price":0.061201,"market_cap":1589668886,"market_cap_rank":60,"fully_diluted_valuation":1589907517,"total_volume":73890235,"high_24h":0.063017,"low_24h":0.059055,"price_change_24h":-0.001815365929803414,"price_change_percentage_24h":-2.88077,"market_cap_change_24h":-41747691.28885174,"market_cap_change_percentage_24h":-2.55898,"circulating_supply":25990798430.54507,"total_supply":25994699998.14652,"max_supply":28704026601.0,"ath":0.207411,"ath_change_percentage":-70.55944,"ath_date":"2024-08-01T00:40:47.164Z","atl":0.00017105,"atl_change_percentage":35598.97869,"atl_date":"2022-05-26T14:42:59.316Z","roi":null,"last_updated":"2025-04-09T16:07:28.225Z"},{"id":"ethena","symbol":"ena","name":"Ethena","image":"https://coin-images.coingecko.com/coins/images/36530/large/ethena.png?1711701436","current_price":0.284953,"market_cap":1579563763,"market_cap_rank":61,"fully_diluted_valuation":4266688836,"total_volume":185608541,"high_24h":0.294278,"low_24h":0.264125,"price_change_24h":-0.009325144607431168,"price_change_percentage_24h":-3.16882,"market_cap_change_24h":-59208312.63992548,"market_cap_change_percentage_24h":-3.61297,"circulating_supply":5553125000.0,"total_supply":15000000000.0,"max_supply":null,"ath":1.52,"ath_change_percentage":-81.25509,"ath_date":"2024-04-11T13:15:15.057Z","atl":0.195078,"atl_change_percentage":45.83491,"atl_date":"2024-09-06T21:04:48.253Z","roi":null,"last_updated":"2025-04-09T16:07:27.099Z"},{"id":"render-token","symbol":"render","name":"Render","image":"https://coin-images.coingecko.com/coins/images/11636/large/rndr.png?1696511529","current_price":2.95,"market_cap":1526593971,"market_cap_rank":62,"fully_diluted_valuation":1570117381,"total_volume":283108880,"high_24h":3.02,"low_24h":2.73,"price_change_24h":-0.06784069798652892,"price_change_percentage_24h":-2.24727,"market_cap_change_24h":-39073409.04584861,"market_cap_change_percentage_24h":-2.49564,"circulating_supply":517716590.0562826,"total_supply":532476763.3362826,"max_supply":null,"ath":13.53,"ath_change_percentage":-78.22471,"ath_date":"2024-03-17T16:30:24.636Z","atl":0.03665669,"atl_change_percentage":7940.05783,"atl_date":"2020-06-16T13:22:25.900Z","roi":null,"last_updated":"2025-04-09T16:07:32.185Z"},{"id":"official-trump","symbol":"trump","name":"Official Trump","image":"https://coin-images.coingecko.com/coins/images/53746/large/trump.png?1737171561","current_price":7.63,"market_cap":1522983179,"market_cap_rank":63,"fully_diluted_valuation":7614916785,"total_volume":607509855,"high_24h":7.77,"low_24h":7.26,"price_change_24h":-0.13071252694585134,"price_change_percentage_24h":-1.68344,"market_cap_change_24h":-35535259.15064597,"market_cap_change_percentage_24h":-2.28007,"circulating_supply":199999976.636,"total_supply":1000000000.0,"max_supply":1000000000.0,"ath":73.43,"ath_change_percentage":-89.60391,"ath_date":"2025-01-19T11:50:34.806Z","atl":4.29,"atl_change_percentage":77.91879,"atl_date":"2025-01-18T03:40:29.231Z","roi":null,"last_updated":"2025-04-09T16:07:31.335Z"},{"id":"filecoin","symbol":"fil","name":"Filecoin","image":"https://coin-images.coingecko.com/coins/images/12817/large/filecoin.png?1696512609","current_price":2.33,"market_cap":1509955549,"market_cap_rank":64,"fully_diluted_valuation":4566634961,"total_volume":152550420,"high_24h":2.35,"low_24h":2.18,"price_change_24h":-0.005098956374950614,"price_change_percentage_24h":-0.21796,"market_cap_change_24h":-5691288.44257164,"market_cap_change_percentage_24h":-0.3755,"circulating_supply":647931581.0,"total_supply":1959572261.0,"max_supply":1959572293.0,"ath":236.84,"ath_change_percentage":-99.0175,"ath_date":"2021-04-01T13:29:41.564Z","atl":2.14,"atl_change_percentage":8.51079,"atl_date":"2025-04-07T07:06:32.125Z","roi":null,"last_updated":"2025-04-09T16:07:27.279Z"},{"id":"polygon-ecosystem-token","symbol":"pol","name":"POL (ex-MATIC)","image":"https://coin-images.coingecko.com/coins/images/32440/large/polygon.png?1698233684","current_price":0.172163,"market_cap":1486285584,"market_cap_rank":65,"fully_diluted_valuation":1786432842,"total_volume":76425950,"high_24h":0.175297,"low_24h":0.162449,"price_change_24h":-0.003133616609850121,"price_change_percentage_24h":-1.7876,"market_cap_change_24h":-29709005.913254738,"market_cap_change_percentage_24h":-1.9597,"circulating_supply":8651686074.295946,"total_supply":10398846835.30774,"max_supply":null,"ath":1.29,"ath_change_percentage":-86.64144,"ath_date":"2024-03-13T18:55:06.692Z","atl":0.153392,"atl_change_percentage":12.13076,"atl_date":"2025-04-07T07:06:08.017Z","roi":null,"last_updated":"2025-04-09T16:07:31.620Z"},{"id":"celestia","symbol":"tia","name":"Celestia","image":"https://coin-images.coingecko.com/coins/images/31967/large/tia.jpg?1696530772","current_price":2.32,"market_cap":1374022015,"market_cap_rank":66,"fully_diluted_valuation":2582915087,"total_volume":98328863,"high_24h":2.45,"low_24h":2.25,"price_change_24h":-0.12440860240073848,"price_change_percentage_24h":-5.08316,"market_cap_change_24h":-73805876.36153126,"market_cap_change_percentage_24h":-5.0977,"circulating_supply":592769081.650111,"total_supply":1114299616.438005,"max_supply":null,"ath":20.85,"ath_change_percentage":-88.8773,"ath_date":"2024-02-10T14:30:02.495Z","atl":2.08,"atl_change_percentage":11.31173,"atl_date":"2023-10-31T15:14:31.951Z","roi":null,"last_updated":"2025-04-09T16:07:35.507Z"},{"id":"algorand","symbol":"algo","name":"Algorand","image":"https://coin-images.coingecko.com/coins/images/4380/large/download.png?1696504978","current_price":0.159808,"market_cap":1366571973,"market_cap_rank":67,"fully_diluted_valuation":1366571973,"total_volume":120107474,"high_24h":0.166749,"low_24h":0.149745,"price_change_24h":-0.006940936686616106,"price_change_percentage_24h":-4.1625,"market_cap_change_24h":-61985376.328906775,"market_cap_change_percentage_24h":-4.33902,"circulating_supply":8559385715.642812,"total_supply":8559385715.642812,"max_supply":10000000000.0,"ath":3.56,"ath_change_percentage":-95.51406,"ath_date":"2019-06-20T14:51:19.480Z","atl":0.087513,"atl_change_percentage":82.54485,"atl_date":"2023-09-11T19:42:08.247Z","roi":{"times":-0.9334132927478824,"currency":"usd","percentage":-93.34132927478824},"last_updated":"2025-04-09T16:07:34.126Z"},{"id":"arbitrum","symbol":"arb","name":"Arbitrum","image":"https://coin-images.coingecko.com/coins/images/16547/large/arb.jpg?1721358242","current_price":0.275925,"market_cap":1273683035,"market_cap_rank":68,"fully_diluted_valuation":2758135423,"total_volume":198741675,"high_24h":0.27662,"low_24h":0.256813,"price_change_24h":0.00378076,"price_change_percentage_24h":1.38925,"market_cap_change_24h":16461844,"market_cap_change_percentage_24h":1.30938,"circulating_supply":4617913336.0,"total_supply":10000000000.0,"max_supply":10000000000.0,"ath":2.39,"ath_change_percentage":-88.46197,"ath_date":"2024-01-12T12:29:59.231Z","atl":0.245747,"atl_change_percentage":12.22582,"atl_date":"2025-04-07T07:01:34.124Z","roi":null,"last_updated":"2025-04-09T16:07:34.494Z"},{"id":"sonic-3","symbol":"s","name":"Sonic (prev. FTM)","image":"https://coin-images.coingecko.com/coins/images/38108/large/200x200_Sonic_Logo.png?1734679256","current_price":0.400882,"market_cap":1272074442,"market_cap_rank":69,"fully_diluted_valuation":1272074442,"total_volume":180482349,"high_24h":0.425424,"low_24h":0.38237,"price_change_24h":-0.024542043462998042,"price_change_percentage_24h":-5.76885,"market_cap_change_24h":-78368165.49675345,"market_cap_change_percentage_24h":-5.80315,"circulating_supply":3175000000.0,"total_supply":3175000000.0,"max_supply":null,"ath":1.029,"ath_change_percentage":-61.0702,"ath_date":"2025-01-04T21:35:44.705Z","atl":0.359647,"atl_change_percentage":11.43464,"atl_date":"2025-02-03T02:11:37.229Z","roi":null,"last_updated":"2025-04-09T16:07:33.540Z"},{"id":"solv-btc","symbol":"solvbtc","name":"Solv Protocol SolvBTC","image":"https://coin-images.coingecko.com/coins/images/36800/large/solvBTC.png?1719810684","current_price":77102,"market_cap":1268698719,"market_cap_rank":70,"fully_diluted_valuation":1268775704,"total_volume":2609540,"high_24h":78201,"low_24h":74735,"price_change_24h":-1099.13834632191,"price_change_percentage_24h":-1.40553,"market_cap_change_24h":-16112199.379506588,"market_cap_change_percentage_24h":-1.25405,"circulating_supply":16466.31111549172,"total_supply":16467.31029514172,"max_supply":21000000.0,"ath":108929,"ath_change_percentage":-29.25505,"ath_date":"2025-01-20T07:17:19.296Z","atl":49058,"atl_change_percentage":57.08403,"atl_date":"2024-08-05T06:28:45.311Z","roi":null,"last_updated":"2025-04-09T16:07:33.033Z"},{"id":"jupiter-perpetuals-liquidity-provider-token","symbol":"jlp","name":"Jupiter Perpetuals Liquidity Provider Token","image":"https://coin-images.coingecko.com/coins/images/33094/large/jlp.png?1700631386","current_price":3.42,"market_cap":1226154924,"market_cap_rank":71,"fully_diluted_valuation":1226154924,"total_volume":43858471,"high_24h":3.44,"low_24h":3.32,"price_change_24h":-0.013153952648907286,"price_change_percentage_24h":-0.38277,"market_cap_change_24h":-6374436.719506741,"market_cap_change_percentage_24h":-0.51718,"circulating_supply":358448109.064359,"total_supply":358448109.064359,"max_supply":null,"ath":5.03,"ath_change_percentage":-31.90302,"ath_date":"2025-01-19T14:31:08.348Z","atl":0.146839,"atl_change_percentage":2231.44724,"atl_date":"2023-11-24T05:55:06.706Z","roi":null,"last_updated":"2025-04-09T16:07:27.910Z"},{"id":"kucoin-shares","symbol":"kcs","name":"KuCoin","image":"https://coin-images.coingecko.com/coins/images/1047/large/sa9z79.png?1696502152","current_price":9.68,"market_cap":1209022531,"market_cap_rank":72,"fully_diluted_valuation":1378226237,"total_volume":2242775,"high_24h":9.67,"low_24h":8.78,"price_change_24h":0.360913,"price_change_percentage_24h":3.87133,"market_cap_change_24h":41543753,"market_cap_change_percentage_24h":3.55842,"circulating_supply":125043917.8513356,"total_supply":142543917.8513356,"max_supply":null,"ath":28.83,"ath_change_percentage":-66.37502,"ath_date":"2021-12-01T15:09:35.541Z","atl":0.342863,"atl_change_percentage":2727.381,"atl_date":"2019-02-07T00:00:00.000Z","roi":null,"last_updated":"2025-04-09T16:07:27.632Z"},{"id":"story-2","symbol":"ip","name":"Story","image":"https://coin-images.coingecko.com/coins/images/54035/large/Transparent_bg.png?1738075331","current_price":4.35,"market_cap":1121924666,"market_cap_rank":73,"fully_diluted_valuation":4334704754,"total_volume":97277944,"high_24h":4.34,"low_24h":3.89,"price_change_24h":0.168001,"price_change_percentage_24h":4.02093,"market_cap_change_24h":32313516,"market_cap_change_percentage_24h":2.9656,"circulating_supply":259477388.3,"total_supply":1002525305.3,"max_supply":null,"ath":7.31,"ath_change_percentage":-41.11225,"ath_date":"2025-02-26T16:11:25.410Z","atl":1.0,"atl_change_percentage":330.5509,"atl_date":"2025-02-14T03:11:08.309Z","roi":null,"last_updated":"2025-04-09T16:07:35.454Z"},{"id":"maker","symbol":"mkr","name":"Maker","image":"https://coin-images.coingecko.com/coins/images/1364/large/Mark_Maker.png?1696502423","current_price":1254.04,"market_cap":1056823884,"market_cap_rank":74,"fully_diluted_valuation":1089418431,"total_volume":158003142,"high_24h":1254.51,"low_24h":1181.2,"price_change_24h":9.66,"price_change_percentage_24h":0.77662,"market_cap_change_24h":1951480,"market_cap_change_percentage_24h":0.185,"circulating_supply":845224.9995937803,"total_supply":871293.4169004256,"max_supply":1005577.0,"ath":6292.31,"ath_change_percentage":-80.13294,"ath_date":"2021-05-03T21:54:29.333Z","atl":168.36,"atl_change_percentage":642.52549,"atl_date":"2020-03-16T20:52:36.527Z","roi":null,"last_updated":"2025-04-09T16:07:29.514Z"},{"id":"fetch-ai","symbol":"fet","name":"Artificial Superintelligence Alliance","image":"https://coin-images.coingecko.com/coins/images/5681/large/ASI.png?1719827289","current_price":0.393807,"market_cap":1024627634,"market_cap_rank":75,"fully_diluted_valuation":1067711747,"total_volume":134672162,"high_24h":0.397444,"low_24h":0.364614,"price_change_24h":0.00087237,"price_change_percentage_24h":0.22202,"market_cap_change_24h":1753676,"market_cap_change_percentage_24h":0.17145,"circulating_supply":2604959126.672,"total_supply":2714493896.672,"max_supply":2714493896.672,"ath":3.45,"ath_change_percentage":-88.61594,"ath_date":"2024-03-28T17:21:18.050Z","atl":0.00816959,"atl_change_percentage":4713.24055,"atl_date":"2020-03-13T02:24:18.347Z","roi":{"times":3.5421837515325953,"currency":"usd","percentage":354.2183751532595},"last_updated":"2025-04-09T16:07:26.871Z"},{"id":"optimism","symbol":"op","name":"Optimism","image":"https://coin-images.coingecko.com/coins/images/25244/large/Optimism.png?1696524385","current_price":0.612344,"market_cap":1014394401,"market_cap_rank":76,"fully_diluted_valuation":2629132920,"total_volume":204218314,"high_24h":0.616792,"low_24h":0.571036,"price_change_24h":0.01094366,"price_change_percentage_24h":1.8197,"market_cap_change_24h":17383517,"market_cap_change_percentage_24h":1.74356,"circulating_supply":1657120774.0,"total_supply":4294967296.0,"max_supply":4294967296.0,"ath":4.84,"ath_change_percentage":-87.37062,"ath_date":"2024-03-06T08:35:50.817Z","atl":0.402159,"atl_change_percentage":52.13037,"atl_date":"2022-06-18T20:54:52.178Z","roi":null,"last_updated":"2025-04-09T16:07:31.748Z"},{"id":"eos","symbol":"eos","name":"EOS","image":"https://coin-images.coingecko.com/coins/images/738/large/CG_EOS_Icon.png?1731705232","current_price":0.669243,"market_cap":1008997074,"market_cap_rank":77,"fully_diluted_valuation":1396871057,"total_volume":301677595,"high_24h":0.713288,"low_24h":0.639506,"price_change_24h":-0.044044941529871484,"price_change_percentage_24h":-6.17492,"market_cap_change_24h":-72605911.94686067,"market_cap_change_percentage_24h":-6.71281,"circulating_supply":1516885789.1746,"total_supply":2100000000.0,"max_supply":2100000000.0,"ath":22.71,"ath_change_percentage":-97.06968,"ath_date":"2018-04-29T07:50:33.540Z","atl":0.402746,"atl_change_percentage":65.2441,"atl_date":"2024-11-04T21:55:59.771Z","roi":{"times":-0.323996815744652,"currency":"usd","percentage":-32.399681574465205},"last_updated":"2025-04-09T16:07:26.935Z"},{"id":"usdt0","symbol":"usdt0","name":"USDT0","image":"https://coin-images.coingecko.com/coins/images/53705/large/usdt0.jpg?1737086183","current_price":0.998591,"market_cap":1000582272,"market_cap_rank":78,"fully_diluted_valuation":1000582272,"total_volume":146296545,"high_24h":1.01,"low_24h":0.99484,"price_change_24h":-0.000944614942740452,"price_change_percentage_24h":-0.09451,"market_cap_change_24h":-1281770.1022583246,"market_cap_change_percentage_24h":-0.12794,"circulating_supply":1002355334.797728,"total_supply":1002359885.52307,"max_supply":null,"ath":1.052,"ath_change_percentage":-5.0803,"ath_date":"2025-01-23T22:34:53.341Z","atl":0.975737,"atl_change_percentage":2.34225,"atl_date":"2025-02-28T01:35:58.101Z","roi":null,"last_updated":"2025-04-09T16:07:31.181Z"},{"id":"xdce-crowd-sale","symbol":"xdc","name":"XDC Network","image":"https://coin-images.coingecko.com/coins/images/2912/large/xdc-icon.png?1696503661","current_price":0.063329,"market_cap":991869252,"market_cap_rank":79,"fully_diluted_valuation":2399608276,"total_volume":52314881,"high_24h":0.066334,"low_24h":0.062014,"price_change_24h":-0.002970755242295342,"price_change_percentage_24h":-4.48081,"market_cap_change_24h":-48481442.016908884,"market_cap_change_percentage_24h":-4.66011,"circulating_supply":15700600627.05,"total_supply":37984136034.9,"max_supply":null,"ath":0.192754,"ath_change_percentage":-67.23633,"ath_date":"2021-08-21T04:39:48.324Z","atl":0.00039532,"atl_change_percentage":15875.32265,"atl_date":"2019-07-22T00:00:00.000Z","roi":{"times":4.664304621919416,"currency":"eth","percentage":466.4304621919416},"last_updated":"2025-04-09T16:07:30.407Z"},{"id":"jupiter-exchange-solana","symbol":"jup","name":"Jupiter","image":"https://coin-images.coingecko.com/coins/images/34188/large/jup.png?1704266489","current_price":0.34854,"market_cap":990864497,"market_cap_rank":80,"fully_diluted_valuation":2438500375,"total_volume":77744675,"high_24h":0.350172,"low_24h":0.318264,"price_change_24h":0.00889422,"price_change_percentage_24h":2.61868,"market_cap_change_24h":25033988,"market_cap_change_percentage_24h":2.59196,"circulating_supply":2844383333.32,"total_supply":6999978143.788602,"max_supply":10000000000.0,"ath":2.0,"ath_change_percentage":-82.59261,"ath_date":"2024-01-31T15:02:47.304Z","atl":0.306358,"atl_change_percentage":13.64155,"atl_date":"2025-04-07T06:56:22.719Z","roi":null,"last_updated":"2025-04-09T16:07:29.723Z"},{"id":"nexo","symbol":"nexo","name":"NEXO","image":"https://coin-images.coingecko.com/coins/images/3695/large/CG-nexo-token-200x200_2x.png?1730414360","current_price":0.96804,"market_cap":966551516,"market_cap_rank":81,"fully_diluted_valuation":966551516,"total_volume":19013871,"high_24h":0.976147,"low_24h":0.907895,"price_change_24h":-0.00573360779063814,"price_change_percentage_24h":-0.5888,"market_cap_change_24h":-7180070.7198547125,"market_cap_change_percentage_24h":-0.73738,"circulating_supply":1000000000.0,"total_supply":1000000000.0,"max_supply":1000000000.0,"ath":4.07,"ath_change_percentage":-76.2474,"ath_date":"2021-05-12T14:37:47.535Z","atl":0.04515276,"atl_change_percentage":2039.95504,"atl_date":"2018-09-13T00:00:00.000Z","roi":{"times":8.680401031915434,"currency":"usd","percentage":868.0401031915434},"last_updated":"2025-04-09T16:07:30.430Z"},{"id":"binance-peg-weth","symbol":"weth","name":"Binance-Peg WETH","image":"https://coin-images.coingecko.com/coins/images/39580/large/weth.png?1723006716","current_price":1487.51,"market_cap":898764941,"market_cap_rank":82,"fully_diluted_valuation":898764941,"total_volume":41569407,"high_24h":1529.54,"low_24h":1394.32,"price_change_24h":-42.02527289506247,"price_change_percentage_24h":-2.74758,"market_cap_change_24h":-25668039.57032025,"market_cap_change_percentage_24h":-2.77663,"circulating_supply":604999.999959841,"total_supply":604999.999959841,"max_supply":null,"ath":4098.26,"ath_change_percentage":-63.75134,"ath_date":"2024-12-06T20:27:27.286Z","atl":1394.32,"atl_change_percentage":6.54414,"atl_date":"2025-04-09T01:32:41.942Z","roi":null,"last_updated":"2025-04-09T16:07:35.333Z"},{"id":"binance-staked-sol","symbol":"bnsol","name":"Binance Staked SOL","image":"https://coin-images.coingecko.com/coins/images/40132/large/bnsol.png?1725968367","current_price":111.26,"market_cap":896131445,"market_cap_rank":83,"fully_diluted_valuation":896131445,"total_volume":5049962,"high_24h":112.28,"low_24h":105.18,"price_change_24h":-0.5068608002734862,"price_change_percentage_24h":-0.45351,"market_cap_change_24h":-3905355.112785101,"market_cap_change_percentage_24h":-0.43391,"circulating_supply":8054538.652638778,"total_supply":8054538.652638778,"max_supply":null,"ath":297.96,"ath_change_percentage":-62.68153,"ath_date":"2025-01-19T11:30:53.744Z","atl":100.21,"atl_change_percentage":10.95907,"atl_date":"2025-04-07T06:56:20.488Z","roi":null,"last_updated":"2025-04-09T16:07:35.535Z"},{"id":"dexe","symbol":"dexe","name":"DeXe","image":"https://coin-images.coingecko.com/coins/images/12713/large/DEXE_token_logo.png?1696512514","current_price":15.55,"market_cap":888328896,"market_cap_rank":84,"fully_diluted_valuation":1501263704,"total_volume":10180907,"high_24h":15.82,"low_24h":15.44,"price_change_24h":-0.26477257549298727,"price_change_percentage_24h":-1.67394,"market_cap_change_24h":-15567443.526327133,"market_cap_change_percentage_24h":-1.72226,"circulating_supply":57103774.56313077,"total_supply":96504599.33609451,"max_supply":null,"ath":32.38,"ath_change_percentage":-51.97274,"ath_date":"2021-03-08T13:29:57.935Z","atl":0.671563,"atl_change_percentage":2215.74352,"atl_date":"2020-11-06T19:31:40.144Z","roi":null,"last_updated":"2025-04-09T16:07:26.149Z"},{"id":"quant-network","symbol":"qnt","name":"Quant","image":"https://coin-images.coingecko.com/coins/images/3370/large/5ZOu7brX_400x400.jpg?1696504070","current_price":60.12,"market_cap":874148846,"market_cap_rank":85,"fully_diluted_valuation":878254894,"total_volume":40228472,"high_24h":62.89,"low_24h":58.9,"price_change_24h":-2.3861706457309566,"price_change_percentage_24h":-3.81778,"market_cap_change_24h":-38717399.408711076,"market_cap_change_percentage_24h":-4.2413,"circulating_supply":14544176.164091088,"total_supply":14612493.0,"max_supply":14612493.0,"ath":427.42,"ath_change_percentage":-85.92688,"ath_date":"2021-09-11T09:15:00.668Z","atl":0.215773,"atl_change_percentage":27777.23999,"atl_date":"2018-08-23T00:00:00.000Z","roi":{"times":16.386693442690195,"currency":"eth","percentage":1638.6693442690193},"last_updated":"2025-04-09T16:07:32.202Z"},{"id":"kelp-dao-restaked-eth","symbol":"rseth","name":"Kelp DAO Restaked ETH","image":"https://coin-images.coingecko.com/coins/images/33800/large/Icon___Dark.png?1702991855","current_price":1547.15,"market_cap":868822853,"market_cap_rank":86,"fully_diluted_valuation":868822853,"total_volume":1079817,"high_24h":1593.05,"low_24h":1459.69,"price_change_24h":-45.44274199515303,"price_change_percentage_24h":-2.85338,"market_cap_change_24h":-25994478.46087396,"market_cap_change_percentage_24h":-2.905,"circulating_supply":561527.4530649718,"total_supply":561527.4588250446,"max_supply":null,"ath":4216.2,"ath_change_percentage":-63.30597,"ath_date":"2024-12-06T20:31:16.142Z","atl":1459.69,"atl_change_percentage":5.98781,"atl_date":"2025-04-09T01:45:22.546Z","roi":null,"last_updated":"2025-04-09T16:07:27.739Z"},{"id":"binance-bridged-usdc-bnb-smart-chain","symbol":"usdc","name":"Binance Bridged USDC (BNB Smart Chain)","image":"https://coin-images.coingecko.com/coins/images/35220/large/USDC.jpg?1707919050","current_price":1.0,"market_cap":849032154,"market_cap_rank":87,"fully_diluted_valuation":849032154,"total_volume":32975720,"high_24h":1.005,"low_24h":0.994131,"price_change_24h":0.00055795,"price_change_percentage_24h":0.05582,"market_cap_change_24h":-51877.80837106705,"market_cap_change_percentage_24h":-0.00611,"circulating_supply":848999999.8398039,"total_supply":848999999.8398039,"max_supply":null,"ath":1.031,"ath_change_percentage":-2.94993,"ath_date":"2024-03-05T20:15:29.285Z","atl":0.942892,"atl_change_percentage":6.1251,"atl_date":"2024-12-05T22:30:25.440Z","roi":null,"last_updated":"2025-04-09T16:07:34.553Z"},{"id":"blockstack","symbol":"stx","name":"Stacks","image":"https://coin-images.coingecko.com/coins/images/2069/large/Stacks_Logo_png.png?1709979332","current_price":0.554659,"market_cap":841485113,"market_cap_rank":88,"fully_diluted_valuation":841485113,"total_volume":42145320,"high_24h":0.5627,"low_24h":0.520382,"price_change_24h":-0.008040865162496802,"price_change_percentage_24h":-1.42898,"market_cap_change_24h":-14712432.317851901,"market_cap_change_percentage_24h":-1.71835,"circulating_supply":1520747741.33098,"total_supply":1520762739.33098,"max_supply":1818000000.0,"ath":3.86,"ath_change_percentage":-85.68322,"ath_date":"2024-04-01T12:34:58.342Z","atl":0.04559639,"atl_change_percentage":1113.35566,"atl_date":"2020-03-13T02:29:26.415Z","roi":{"times":3.622160188980994,"currency":"usd","percentage":362.21601889809943},"last_updated":"2025-04-09T16:07:34.819Z"},{"id":"polygon-bridged-usdt-polygon","symbol":"usdt","name":"Polygon Bridged USDT (Polygon)","image":"https://coin-images.coingecko.com/coins/images/35023/large/USDT.png?1707233644","current_price":0.999089,"market_cap":814163476,"market_cap_rank":89,"fully_diluted_valuation":814163476,"total_volume":33524166,"high_24h":0.999643,"low_24h":0.998826,"price_change_24h":-0.000384772472128758,"price_change_percentage_24h":-0.0385,"market_cap_change_24h":9935064,"market_cap_change_percentage_24h":1.23535,"circulating_supply":814948122.274822,"total_supply":814948122.274822,"max_supply":null,"ath":1.027,"ath_change_percentage":-2.69571,"ath_date":"2024-04-14T06:51:56.926Z","atl":0.945933,"atl_change_percentage":5.62105,"atl_date":"2024-12-05T22:30:30.789Z","roi":null,"last_updated":"2025-04-09T16:07:32.575Z"},{"id":"worldcoin-wld","symbol":"wld","name":"Worldcoin","image":"https://coin-images.coingecko.com/coins/images/31069/large/worldcoin.jpeg?1696529903","current_price":0.640505,"market_cap":793722994,"market_cap_rank":90,"fully_diluted_valuation":6387317497,"total_volume":150363061,"high_24h":0.641174,"low_24h":0.595981,"price_change_24h":-0.000669082239329599,"price_change_percentage_24h":-0.10435,"market_cap_change_24h":-1983898.3916635513,"market_cap_change_percentage_24h":-0.24933,"circulating_supply":1242654673.732694,"total_supply":10000000000.0,"max_supply":10000000000.0,"ath":11.74,"ath_change_percentage":-94.55488,"ath_date":"2024-03-10T00:10:42.330Z","atl":0.583741,"atl_change_percentage":9.51603,"atl_date":"2025-04-07T07:06:11.379Z","roi":null,"last_updated":"2025-04-09T16:07:31.137Z"},{"id":"paypal-usd","symbol":"pyusd","name":"PayPal USD","image":"https://coin-images.coingecko.com/coins/images/31212/large/PYUSD_Logo_%282%29.png?1696530039","current_price":0.999556,"market_cap":787412361,"market_cap_rank":91,"fully_diluted_valuation":787412361,"total_volume":155895891,"high_24h":1.001,"low_24h":0.998408,"price_change_24h":-5.8352611707502e-05,"price_change_percentage_24h":-0.00584,"market_cap_change_24h":-6952413.983045578,"market_cap_change_percentage_24h":-0.87522,"circulating_supply":788033445.356147,"total_supply":788033445.356147,"max_supply":null,"ath":1.021,"ath_change_percentage":-2.07545,"ath_date":"2023-10-23T22:44:57.056Z","atl":0.959426,"atl_change_percentage":4.18233,"atl_date":"2024-12-05T22:31:13.430Z","roi":null,"last_updated":"2025-04-09T16:07:32.495Z"},{"id":"usual-usd","symbol":"usd0","name":"Usual USD","image":"https://coin-images.coingecko.com/coins/images/38272/large/USD0LOGO.png?1716962811","current_price":0.99821,"market_cap":776540373,"market_cap_rank":92,"fully_diluted_valuation":776540373,"total_volume":13887318,"high_24h":0.998722,"low_24h":0.997813,"price_change_24h":-0.000453826701036442,"price_change_percentage_24h":-0.04544,"market_cap_change_24h":804948,"market_cap_change_percentage_24h":0.10377,"circulating_supply":777933457.4404365,"total_supply":777933457.4404365,"max_supply":null,"ath":1.33,"ath_change_percentage":-24.70318,"ath_date":"2024-07-12T08:28:59.311Z","atl":0.976415,"atl_change_percentage":2.23215,"atl_date":"2025-01-20T17:07:15.786Z","roi":null,"last_updated":"2025-04-09T16:07:30.326Z"},{"id":"bonk","symbol":"bonk","name":"Bonk","image":"https://coin-images.coingecko.com/coins/images/28600/large/bonk.jpg?1696527587","current_price":1.001e-05,"market_cap":774174497,"market_cap_rank":93,"fully_diluted_valuation":888405520,"total_volume":96809169,"high_24h":1.005e-05,"low_24h":9.23e-06,"price_change_24h":-4.2839223066e-08,"price_change_percentage_24h":-0.42623,"market_cap_change_24h":-4293938.339717388,"market_cap_change_percentage_24h":-0.55159,"circulating_supply":77419592329436.58,"total_supply":88843010803537.8,"max_supply":88843010803537.8,"ath":5.825e-05,"ath_change_percentage":-82.85982,"ath_date":"2024-11-20T04:01:06.465Z","atl":8.6142e-08,"atl_change_percentage":11490.31465,"atl_date":"2022-12-29T22:48:46.755Z","roi":null,"last_updated":"2025-04-09T16:07:34.613Z"},{"id":"movement","symbol":"move","name":"Movement","image":"https://coin-images.coingecko.com/coins/images/39345/large/movement-testnet-token.png?1721878759","current_price":0.312066,"market_cap":763928407,"market_cap_rank":94,"fully_diluted_valuation":3118075131,"total_volume":50377226,"high_24h":0.321738,"low_24h":0.291706,"price_change_24h":-0.009672568995156117,"price_change_percentage_24h":-3.00635,"market_cap_change_24h":-26315664.31673634,"market_cap_change_percentage_24h":-3.33007,"circulating_supply":2450000000.0,"total_supply":10000000000.0,"max_supply":10000000000.0,"ath":1.45,"ath_change_percentage":-78.47019,"ath_date":"2024-12-10T04:05:51.093Z","atl":0.290795,"atl_change_percentage":7.34446,"atl_date":"2025-04-07T06:56:13.803Z","roi":null,"last_updated":"2025-04-09T16:07:30.244Z"},{"id":"tether-gold","symbol":"xaut","name":"Tether Gold","image":"https://coin-images.coingecko.com/coins/images/10481/large/Tether_Gold.png?1696510471","current_price":3091.37,"market_cap":762025373,"market_cap_rank":95,"fully_diluted_valuation":762025373,"total_volume":44232488,"high_24h":3094.72,"low_24h":2986.62,"price_change_24h":79.47,"price_change_percentage_24h":2.63849,"market_cap_change_24h":19388032,"market_cap_change_percentage_24h":2.6107,"circulating_supply":246524.33,"total_supply":246524.33,"max_supply":null,"ath":3190.62,"ath_change_percentage":-3.11193,"ath_date":"2025-04-01T00:42:40.216Z","atl":1447.84,"atl_change_percentage":113.51306,"atl_date":"2020-03-19T13:45:41.821Z","roi":null,"last_updated":"2025-04-09T16:07:25.230Z"},{"id":"rocket-pool-eth","symbol":"reth","name":"Rocket Pool ETH","image":"https://coin-images.coingecko.com/coins/images/20764/large/reth.png?1696520159","current_price":1676.34,"market_cap":724951855,"market_cap_rank":96,"fully_diluted_valuation":724951855,"total_volume":18997352,"high_24h":1725.16,"low_24h":1577.04,"price_change_24h":-48.821634263345686,"price_change_percentage_24h":-2.82997,"market_cap_change_24h":-24620995.482408285,"market_cap_change_percentage_24h":-3.28467,"circulating_supply":432484.5940298374,"total_supply":432484.5940298374,"max_supply":null,"ath":4814.31,"ath_change_percentage":-65.19126,"ath_date":"2021-12-01T08:03:50.749Z","atl":887.26,"atl_change_percentage":88.87295,"atl_date":"2022-06-18T20:55:45.957Z","roi":null,"last_updated":"2025-04-09T16:07:32.544Z"},{"id":"flare-networks","symbol":"flr","name":"Flare","image":"https://coin-images.coingecko.com/coins/images/28624/large/FLR-icon200x200.png?1696527609","current_price":0.01135713,"market_cap":714647397,"market_cap_rank":97,"fully_diluted_valuation":1173143475,"total_volume":7741233,"high_24h":0.01168797,"low_24h":0.0110563,"price_change_24h":-0.000330845904513747,"price_change_percentage_24h":-2.83065,"market_cap_change_24h":-20984874.003837228,"market_cap_change_percentage_24h":-2.85263,"circulating_supply":62894123933.06894,"total_supply":103245084732.6007,"max_supply":null,"ath":0.150073,"ath_change_percentage":-92.42322,"ath_date":"2023-01-10T03:14:05.921Z","atl":0.00827405,"atl_change_percentage":37.42598,"atl_date":"2023-10-19T03:35:41.663Z","roi":null,"last_updated":"2025-04-09T16:07:26.905Z"},{"id":"theta-token","symbol":"theta","name":"Theta Network","image":"https://coin-images.coingecko.com/coins/images/2538/large/theta-token-logo.png?1696503349","current_price":0.712755,"market_cap":712257916,"market_cap_rank":98,"fully_diluted_valuation":712257916,"total_volume":31837943,"high_24h":0.726801,"low_24h":0.662501,"price_change_24h":-0.011129284017586949,"price_change_percentage_24h":-1.53744,"market_cap_change_24h":-11307799.326804519,"market_cap_change_percentage_24h":-1.56279,"circulating_supply":1000000000.0,"total_supply":1000000000.0,"max_supply":1000000000.0,"ath":15.72,"ath_change_percentage":-95.46452,"ath_date":"2021-04-16T13:15:11.190Z","atl":0.04039979,"atl_change_percentage":1664.77156,"atl_date":"2020-03-13T02:24:16.483Z","roi":{"times":3.7517006294215225,"currency":"usd","percentage":375.17006294215224},"last_updated":"2025-04-09T16:07:27.169Z"},{"id":"immutable-x","symbol":"imx","name":"Immutable","image":"https://coin-images.coingecko.com/coins/images/17233/large/immutableX-symbol-BLK-RGB.png?1696516787","current_price":0.394011,"market_cap":705599271,"market_cap_rank":99,"fully_diluted_valuation":787132517,"total_volume":38368155,"high_24h":0.397742,"low_24h":0.363385,"price_change_24h":0.0023033,"price_change_percentage_24h":0.58801,"market_cap_change_24h":-79786.30987262726,"market_cap_change_percentage_24h":-0.01131,"circulating_supply":1792834764.3898141,"total_supply":2000000000.0,"max_supply":2000000000.0,"ath":9.52,"ath_change_percentage":-95.86853,"ath_date":"2021-11-26T01:03:01.536Z","atl":0.353994,"atl_change_percentage":11.10738,"atl_date":"2025-04-07T07:00:54.005Z","roi":null,"last_updated":"2025-04-09T16:07:27.385Z"},{"id":"injective-protocol","symbol":"inj","name":"Injective","image":"https://coin-images.coingecko.com/coins/images/12882/large/Other_200x200.png?1738782212","current_price":7.22,"market_cap":705067737,"market_cap_rank":100,"fully_diluted_valuation":721465048,"total_volume":87025151,"high_24h":7.26,"low_24h":6.79,"price_change_24h":-0.005255348583832919,"price_change_percentage_24h":-0.07278,"market_cap_change_24h":-1721952.3315941095,"market_cap_change_percentage_24h":-0.24363,"circulating_supply":97727220.33,"total_supply":100000000.0,"max_supply":null,"ath":52.62,"ath_change_percentage":-86.30247,"ath_date":"2024-03-14T15:06:22.124Z","atl":0.657401,"atl_change_percentage":996.39867,"atl_date":"2020-11-03T16:19:30.576Z","roi":null,"last_updated":"2025-04-09T16:07:28.424Z"}]